{"meta":{"id":"21-seacroft-halton","name":"21 - Seacroft - Halton (Arriva Yorkshire)","agency_name":"Arriva Yorkshire","agency_noc":"WRAY","bustimesorg":true},"line":{},"stops":{"450011227":{"name":"Field End Road","lon":-1.465122,"lat":53.797123,"bearing":270},"450011236":{"name":"Whitkirk Church","lon":-1.448502,"lat":53.797985,"bearing":90},"450012096":{"name":"Austhorpe Road Croftdale Grove","lon":-1.442833,"lat":53.806507,"bearing":0},"450011229":{"name":"Halton Lidl","lon":-1.471196,"lat":53.795803,"bearing":270},"450012069":{"name":"Manston Park","lon":-1.444356,"lat":53.807339,"bearing":90},"450012859":{"name":"Stocks Approach","lon":-1.45666,"lat":53.816429,"bearing":135},"450011246":{"name":"Irwin Approach","lon":-1.471698,"lat":53.794468,"bearing":180},"450051471":{"name":"Templegate Avenue","lon":-1.46209,"lat":53.793167,"bearing":45},"450014828":{"name":"Ring Road Cross Gates","lon":-1.452737,"lat":53.812042,"bearing":0},"450050045":{"name":"Kingswear Cres Kennerleigh Ave","lon":-1.441532,"lat":53.803875,"bearing":270},"450012068":{"name":"Manston Park","lon":-1.444706,"lat":53.807251,"bearing":270},"450011220":{"name":"Chantry Garth","lon":-1.442921,"lat":53.795254,"bearing":180},"450010781":{"name":"Ring Rd Cross Gates Lane","lon":-1.452593,"lat":53.809132,"bearing":0},"450010789":{"name":"Seacroft The Green","lon":-1.458534,"lat":53.81945,"bearing":180},"450012099":{"name":"Kingswear Cres Kingswear Parade","lon":-1.444736,"lat":53.802643,"bearing":0},"450011243":{"name":"New Temple Gate","lon":-1.469504,"lat":53.791462,"bearing":45},"450011237":{"name":"Garland Drive","lon":-1.442736,"lat":53.797794,"bearing":90},"450011241":{"name":"Temple Gate Drive","lon":-1.46494,"lat":53.792278,"bearing":90},"450014438":{"name":"Ring Road Cross Gates","lon":-1.452402,"lat":53.812168,"bearing":180},"450011218":{"name":"Laurel Hill Avenue","lon":-1.443041,"lat":53.791901,"bearing":90},"450024302":{"name":"School Lane Selby Rd","lon":-1.436212,"lat":53.795177,"bearing":180},"450010247":{"name":"Austhorpe Lane","lon":-1.436915,"lat":53.795979,"bearing":315},"450026298":{"name":"Kingswear Cres Lulworth Cres","lon":-1.441008,"lat":53.799839,"bearing":315},"450010774":{"name":"Queensway","lon":-1.45616,"lat":53.797462,"bearing":270},"450012094":{"name":"Whitkirk Lane","lon":-1.441279,"lat":53.798885,"bearing":225},"450011225":{"name":"Colton Retail Park","lon":-1.4338,"lat":53.795067,"bearing":135},"450011239":{"name":"Templegate Walk","lon":-1.458837,"lat":53.794731,"bearing":45},"450010252":{"name":"Laurel Hill Way","lon":-1.440396,"lat":53.79108,"bearing":315},"450011222":{"name":"High Bank Approach","lon":-1.441596,"lat":53.796757,"bearing":0},"450010773":{"name":"Whitkirk Church","lon":-1.450452,"lat":53.797474,"bearing":270},"450011215":{"name":"Yew Tree Lane","lon":-1.435023,"lat":53.791073,"bearing":90},"450011248":{"name":"Temple Newsam View","lon":-1.471101,"lat":53.792431,"bearing":180},"450010246":{"name":"Colton Retail Park","lon":-1.433473,"lat":53.794537,"bearing":315},"450011228":{"name":"Halton Tesco","lon":-1.469322,"lat":53.79628,"bearing":225},"450014437":{"name":"Ring Rd Barwick Road","lon":-1.452799,"lat":53.814289,"bearing":180},"450010249":{"name":"Chantry Garth","lon":-1.443042,"lat":53.795326,"bearing":0},"450011217":{"name":"Laurel Hill Way","lon":-1.44065,"lat":53.791386,"bearing":135},"450011216":{"name":"School Lane","lon":-1.437939,"lat":53.790897,"bearing":90},"450011221":{"name":"High Bank Approach","lon":-1.441984,"lat":53.796078,"bearing":225},"450024092":{"name":"School La Colton Road East","lon":-1.438373,"lat":53.791412,"bearing":180},"450012857":{"name":"Seacroft The Green","lon":-1.458842,"lat":53.819191,"bearing":0},"450010514":{"name":"Cross Gates Ctr C","lon":-1.448942,"lat":53.80727,"bearing":270},"450011226":{"name":"Wilfred Avenue","lon":-1.459893,"lat":53.797657,"bearing":270},"450012097":{"name":"Austhorpe Road Croftdale Grove","lon":-1.442783,"lat":53.806866,"bearing":180},"450023941":{"name":"Ring Rd Cross Gates Lane","lon":-1.452292,"lat":53.808922,"bearing":180},"450010250":{"name":"Darnley Lane","lon":-1.444174,"lat":53.793499,"bearing":45},"450012801":{"name":"Kingswear Cres Lulworth Cres","lon":-1.44072,"lat":53.799828,"bearing":135},"450011234":{"name":"Queensway","lon":-1.454583,"lat":53.797329,"bearing":90},"450012093":{"name":"York Rd Barwick Road","lon":-1.454585,"lat":53.814747,"bearing":45},"450025302":{"name":"Seacroft Bus Stn C","lon":-1.459724,"lat":53.821449,"bearing":null},"450012864":{"name":"Stocks Approach Hansby Avenue","lon":-1.455392,"lat":53.816944,"bearing":270},"450011235":{"name":"Kingsway","lon":-1.452884,"lat":53.797241,"bearing":90},"450011223":{"name":"Detroit Drive","lon":-1.439493,"lat":53.797314,"bearing":135},"450010775":{"name":"Temple Moor School","lon":-1.462796,"lat":53.797367,"bearing":270},"450011238":{"name":"Temple Gate","lon":-1.456165,"lat":53.797085,"bearing":0},"450010515":{"name":"Cross Gates Ctr D","lon":-1.448729,"lat":53.807369,"bearing":90},"450011213":{"name":"Stile Hill Way","lon":-1.432505,"lat":53.792023,"bearing":0},"450010772":{"name":"Garland Drive","lon":-1.443283,"lat":53.797718,"bearing":270},"450012098":{"name":"Kingswear Cres Kennerleigh Ave","lon":-1.441546,"lat":53.803955,"bearing":90},"450012100":{"name":"Kingswear Cres Kingswear Parade","lon":-1.444483,"lat":53.802326,"bearing":180},"450010248":{"name":"Detroit Drive","lon":-1.439905,"lat":53.797146,"bearing":315},"450011219":{"name":"Darnley Lane","lon":-1.44393,"lat":53.793568,"bearing":225},"450050044":{"name":"Whitkirk Lane","lon":-1.441339,"lat":53.798958,"bearing":45},"450011254":{"name":"Skyliner Roundabout","lon":-1.441818,"lat":53.798321,"bearing":135},"450011224":{"name":"Austhorpe Lane","lon":-1.437182,"lat":53.796459,"bearing":135}},"trips":[[["450011246",1726487668,1726487673,0],["450011248",1726487708,1726487723,1],["450011243",1726487734,1726487756,0],["450011241",1726487794,1726487825,1],["450051471",1726487834,1726487871,0],["450011239",1726487927,1726487931,0],["450011238",1726487992,1726488000,1],["450011234",1726488010,1726488020,1],["450011235",1726488030,1726488041,0],["450011236",1726488056,1726488096,1],["450011237",1726488090,1726488166,0],["450011223",1726488127,1726488206,1],["450011224",1726488159,1726488240,0],["450011225",1726488178,1726488289,1],["450010246",1726488183,1726488301,0],["450024302",1726488276,1726488337,0],["450024092",1726488337,1726488418,0],["450010252",1726488398,1726488444,0],["450011218",1726488432,1726488480,1],["450010250",1726488460,1726488509,0],["450010249",1726488491,1726488542,0],["450011222",1726488519,1726488570,1],["450050044",1726488556,1726488607,0],["450026298",1726488572,1726488622,1],["450012099",1726488636,1726488681,0],["450012098",1726488735,1726488720,0],["450012096",1726488785,1726488840,0],["450012068",1726488833,1726488900,0],["450010514",1726488899,1726488960,0],["450010781",1726489078,1726489080,0],["450014828",1726489110,1726489140,1],["450012864",1726489208,1726489320,0],["450012857",1726489240,1726489440,0],["450025302",1726489487,1726489500,0]],[["450011246",1727092478,1727092473,0],["450011248",1727092529,1727092523,0],["450011243",1727092545,1727092556,1],["450011241",1727092579,1727092625,0],["450051471",1727092611,1727092671,1],["450011239",1727092652,1727092731,0],["450011238",1727092716,1727092800,0],["450011234",1727092781,1727092820,0],["450011235",1727092788,1727092841,1],["450011236",1727092808,1727092896,1],["450011237",1727092833,1727092966,0],["450011223",1727092897,1727093006,0],["450011224",1727092919,1727093040,1],["450011225",1727092950,1727093089,0],["450010246",1727092958,1727093101,1],["450024302",1727092983,1727093137,0],["450024092",1727093131,1727093218,0],["450010252",1727093155,1727093244,1],["450011218",1727093189,1727093280,0],["450010250",1727093215,1727093309,1],["450010249",1727093244,1727093342,0],["450011222",1727093267,1727093370,1],["450050044",1727093297,1727093407,0],["450026298",1727093375,1727093422,0],["450012099",1727093440,1727093481,1],["450012098",1727093483,1727093520,0],["450012096",1727093551,1727093640,0],["450012068",1727093601,1727093700,1],["450010514",1727093651,1727093760,0],["450010781",1727093721,1727093880,0],["450014828",1727093802,1727093940,0],["450012864",1727093855,1727094120,0],["450012857",1727093896,1727094240,0],["450025302",1727094282,1727094300,0]],[["450010515",1726486543,1726486560,0],["450012069",1726486600,1726486606,0],["450012097",1726486632,1726486625,0],["450050045",1726486677,1726486680,1],["450012100",1726486718,1726486730,0],["450012801",1726486795,1726486801,0],["450012094",1726486817,1726486822,1],["450011254",1726486831,1726486836,1],["450011221",1726486880,1726486884,0],["450011220",1726486896,1726486905,1],["450011219",1726486924,1726486943,1],["450011218",1726486951,1726486980,0],["450011217",1726486983,1726487005,1],["450011216",1726487017,1726487032,0],["450011215",1726487044,1726487061,0],["450011213",1726487125,1726487090,0],["450010246",1726487190,1726487133,0],["450010247",1726487230,1726487174,1],["450010248",1726487265,1726487209,0],["450010772",1726487314,1726487243,0],["450010773",1726487352,1726487313,0],["450010774",1726487423,1726487369,0],["450011226",1726487444,1726487405,1],["450010775",1726487461,1726487434,0],["450011227",1726487485,1726487457,1],["450011228",1726487531,1726487500,1],["450011229",1726487552,1726487520,0]],[["450010789",1727091105,1727091046,0],["450012859",1727091139,1727091116,0],["450012093",1727091177,1727091161,0],["450014437",1727091210,1727091186,1],["450014438",1727091272,1727091233,0],["450023941",1727091338,1727091303,1],["450010515",1727091392,1727091360,0],["450012069",1727091434,1727091406,1],["450012097",1727091452,1727091425,0],["450050045",1727091514,1727091480,0],["450012100",1727091567,1727091530,0],["450012801",1727091615,1727091601,1],["450012094",1727091629,1727091622,0],["450011254",1727091641,1727091636,1],["450011221",1727091684,1727091684,0],["450011220",1727091698,1727091705,1],["450011219",1727091725,1727091743,1],["450011218",1727091750,1727091780,0],["450011217",1727091780,1727091805,1],["450011216",1727091812,1727091832,0],["450011215",1727091861,1727091861,1],["450011213",1727091910,1727091890,0],["450010246",1727091993,1727091933,0],["450010247",1727092021,1727091974,1],["450010248",1727092045,1727092009,0],["450010772",1727092060,1727092043,1],["450010773",1727092090,1727092113,0],["450010774",1727092174,1727092169,0],["450011226",1727092196,1727092205,1],["450010775",1727092213,1727092234,0]],[["450010789",1726493529,1726493446,0],["450012859",1726493588,1726493516,1],["450012093",1726493626,1726493561,1],["450014437",1726493647,1726493586,0],["450014438",1726493668,1726493633,1],["450023941",1726493700,1726493703,0],["450010515",1726493778,1726493760,1],["450012069",1726493841,1726493806,1],["450012097",1726493867,1726493825,1],["450050045",1726493942,1726493880,0],["450012100",1726493997,1726493930,1],["450012801",1726494076,1726494001,1],["450012094",1726494099,1726494022,1],["450011254",1726494115,1726494036,0],["450011221",1726494172,1726494084,1],["450011220",1726494197,1726494105,1],["450011219",1726494243,1726494143,1],["450011218",1726494287,1726494180,1],["450011217",1726494331,1726494217,0]],[["450011246",1726574179,1726574073,0],["450011248",1726574200,1726574123,1],["450011243",1726574214,1726574156,1],["450011241",1726574243,1726574225,0],["450051471",1726574316,1726574271,1],["450011239",1726574411,1726574331,0],["450011238",1726574523,1726574400,1],["450011234",1726574555,1726574420,0],["450011235",1726574571,1726574441,1],["450011236",1726574613,1726574496,0],["450011237",1726574653,1726574566,1],["450011223",1726574676,1726574606,0],["450011224",1726574686,1726574640,1],["450011225",1726574700,1726574689,0],["450010246",1726574740,1726574701,1],["450024302",1726574858,1726574737,0],["450024092",1726574902,1726574818,0],["450010252",1726574934,1726574844,1],["450011218",1726574978,1726574880,0],["450010250",1726575007,1726574909,1],["450010249",1726575039,1726574942,0],["450011222",1726575059,1726574970,1],["450050044",1726575085,1726575007,0],["450026298",1726575150,1726575022,0],["450012099",1726575204,1726575081,0],["450012098",1726575279,1726575120,0],["450012096",1726575335,1726575240,0],["450012068",1726575368,1726575300,1],["450010514",1726575402,1726575360,0],["450010781",1726575567,1726575480,0],["450014828",1726575614,1726575540,0],["450012864",1726575676,1726575720,0],["450012857",1726575736,1726575840,0],["450025302",1726575930,1726575900,0]],[["450010789",1726572695,1726572646,0],["450012859",1726572752,1726572716,0],["450012093",1726572811,1726572761,0],["450014437",1726572858,1726572786,0],["450014438",1726572887,1726572833,1],["450023941",1726572930,1726572903,0],["450010515",1726572996,1726572960,0],["450012069",1726573111,1726573006,0],["450012097",1726573122,1726573025,1],["450050045",1726573153,1726573080,0],["450012100",1726573291,1726573130,0],["450012801",1726573324,1726573201,0],["450012094",1726573372,1726573222,1],["450011254",1726573404,1726573236,0],["450011221",1726573455,1726573284,1],["450011220",1726573477,1726573305,0],["450011219",1726573501,1726573343,1],["450011218",1726573524,1726573380,1],["450011217",1726573539,1726573405,0],["450011216",1726573559,1726573432,0],["450011215",1726573602,1726573461,1],["450011213",1726573646,1726573490,1],["450010246",1726573710,1726573533,1],["450010247",1726573772,1726573574,0],["450010248",1726573806,1726573609,0],["450010772",1726573829,1726573643,1],["450010773",1726573875,1726573713,0],["450010774",1726573929,1726573769,1],["450011226",1726573963,1726573805,0],["450010775",1726573981,1726573834,1],["450011227",1726573995,1726573857,1],["450011228",1726574022,1726573900,0]],[["450010789",1726565557,1726565446,0],["450012859",1726565644,1726565516,1],["450012093",1726565700,1726565561,1],["450014437",1726565731,1726565586,0],["450014438",1726565780,1726565633,1],["450023941",1726565853,1726565703,1],["450010515",1726565913,1726565760,1],["450012069",1726565961,1726565806,1],["450012097",1726565980,1726565825,1],["450050045",1726566038,1726565880,1],["450012100",1726566090,1726565930,0],["450012801",1726566139,1726566001,0],["450012094",1726566174,1726566022,1],["450011254",1726566197,1726566036,1],["450011221",1726566277,1726566084,0],["450011220",1726566327,1726566105,0],["450011219",1726566358,1726566143,1],["450011218",1726566388,1726566180,1],["450011217",1726566408,1726566205,1],["450011216",1726566430,1726566232,1],["450011215",1726566454,1726566261,0],["450011213",1726566482,1726566290,1],["450010246",1726566525,1726566333,1],["450010247",1726566565,1726566374,1],["450010248",1726566599,1726566409,1],["450010772",1726566633,1726566443,1],["450010773",1726566701,1726566513,1],["450010774",1726566756,1726566569,1],["450011226",1726566792,1726566605,1],["450010775",1726566820,1726566634,0],["450011227",1726566862,1726566657,0]],[["450010789",1726579883,1726579846,0],["450012859",1726579951,1726579916,1],["450012093",1726579995,1726579961,1],["450014437",1726580019,1726579986,0],["450014438",1726580070,1726580033,0],["450023941",1726580101,1726580103,1],["450010515",1726580127,1726580160,0],["450012069",1726580252,1726580206,0],["450012097",1726580264,1726580225,1],["450050045",1726580300,1726580280,0],["450012100",1726580350,1726580330,1],["450012801",1726580420,1726580401,1],["450012094",1726580441,1726580422,0],["450011254",1726580460,1726580436,1],["450011221",1726580523,1726580484,1],["450011220",1726580551,1726580505,0],["450011219",1726580577,1726580543,1],["450011218",1726580603,1726580580,0],["450011217",1726580633,1726580617,1],["450011216",1726580666,1726580658,0]],[["450051471",1726567103,1726567071,0],["450011239",1726567232,1726567131,0],["450011238",1726567330,1726567200,1],["450011234",1726567358,1726567220,0],["450011235",1726567374,1726567241,1],["450011236",1726567417,1726567296,0],["450011237",1726567457,1726567366,1],["450011223",1726567480,1726567406,1],["450011224",1726567499,1726567440,1],["450011225",1726567527,1726567489,0],["450010246",1726567573,1726567501,1],["450024302",1726567710,1726567537,0],["450024092",1726567774,1726567618,0],["450010252",1726567800,1726567644,1],["450011218",1726567836,1726567680,1],["450010250",1726567864,1726567709,1],["450010249",1726567897,1726567742,1],["450011222",1726567925,1726567770,1],["450050044",1726567962,1726567807,1],["450026298",1726567977,1726567822,1],["450012099",1726568035,1726567881,1],["450012098",1726568074,1726567920,1],["450012096",1726568193,1726568040,0],["450012068",1726568239,1726568100,1],["450010514",1726568286,1726568160,1],["450010781",1726568378,1726568280,0],["450014828",1726568490,1726568340,0]],[["450011246",1726660757,1726660473,0],["450011248",1726660777,1726660523,1],["450011243",1726660791,1726660556,1],["450011241",1726660819,1726660625,1],["450051471",1726660838,1726660671,1],["450011239",1726660863,1726660731,1],["450011238",1726660891,1726660800,0],["450011234",1726660900,1726660820,1],["450011235",1726660910,1726660841,1],["450011236",1726660936,1726660896,1],["450011237",1726660968,1726660966,0],["450011223",1726661000,1726661006,1],["450011224",1726661028,1726661040,0],["450011225",1726661048,1726661089,0],["450010246",1726661084,1726661101,1],["450024302",1726661191,1726661137,0],["450024092",1726661299,1726661218,0],["450010252",1726661328,1726661244,1],["450011218",1726661369,1726661280,0],["450010250",1726661400,1726661309,1],["450010249",1726661435,1726661342,0],["450011222",1726661463,1726661370,1],["450050044",1726661499,1726661407,0],["450026298",1726661522,1726661422,1],["450012099",1726661613,1726661481,0],["450012098",1726661681,1726661520,0],["450012096",1726661739,1726661640,0],["450012068",1726661788,1726661700,0],["450010514",1726661862,1726661760,0],["450010781",1726661942,1726661880,0],["450014828",1726662006,1726661940,0],["450012864",1726662028,1726662120,0],["450012857",1726662134,1726662240,0],["450025302",1726662173,1726662300,0]],[["450010789",1726659041,1726659046,0],["450012859",1726659103,1726659116,0],["450012093",1726659143,1726659161,1],["450014437",1726659165,1726659186,0],["450014438",1726659189,1726659233,1],["450023941",1726659225,1726659303,0],["450010515",1726659349,1726659360,0],["450012069",1726659480,1726659406,0],["450012097",1726659506,1726659425,1],["450050045",1726659582,1726659480,0],["450012100",1726659653,1726659530,0],["450012801",1726659708,1726659601,0],["450012094",1726659770,1726659622,0],["450011254",1726659780,1726659636,1],["450011221",1726659814,1726659684,0],["450011220",1726659834,1726659705,1],["450011219",1726659870,1726659743,1],["450011218",1726659905,1726659780,0],["450011217",1726659929,1726659805,1],["450011216",1726659955,1726659832,0],["450011215",1726660000,1726659861,1],["450011213",1726660045,1726659890,0],["450010246",1726660105,1726659933,0],["450010247",1726660121,1726659974,1],["450010248",1726660134,1726660009,0],["450010772",1726660170,1726660043,0],["450010773",1726660249,1726660113,0],["450010774",1726660282,1726660169,1],["450011226",1726660303,1726660205,0],["450010775",1726660331,1726660234,1],["450011227",1726660353,1726660257,1],["450011228",1726660395,1726660300,0]],[["450010789",1726651987,1726651846,0],["450012859",1726652030,1726651916,1],["450012093",1726652057,1726651961,1],["450014437",1726652073,1726651986,1],["450014438",1726652101,1726652033,1],["450023941",1726652144,1726652103,1],["450010515",1726652179,1726652160,1],["450012069",1726652207,1726652206,1],["450012097",1726652219,1726652225,1],["450050045",1726652252,1726652280,1],["450012100",1726652283,1726652330,0],["450012801",1726652402,1726652401,1],["450012094",1726652437,1726652422,0],["450011254",1726652473,1726652436,0],["450011221",1726652533,1726652484,1],["450011220",1726652559,1726652505,0],["450011219",1726652590,1726652543,1],["450011218",1726652620,1726652580,0],["450011217",1726652644,1726652605,1],["450011216",1726652669,1726652632,0],["450011215",1726652720,1726652661,1],["450011213",1726652771,1726652690,1],["450010246",1726652847,1726652733,1],["450010247",1726652919,1726652774,0],["450010248",1726652974,1726652809,0],["450010772",1726652999,1726652843,1],["450010773",1726653052,1726652913,1],["450010774",1726653093,1726652969,1],["450011226",1726653120,1726653005,1],["450010775",1726653142,1726653034,1],["450011227",1726653159,1726653057,0]],[["450012859",1726666556,1726666316,0],["450012093",1726666583,1726666361,1],["450014437",1726666598,1726666386,0],["450014438",1726666634,1726666433,0]],[["450011241",1726653400,1726653425,0],["450051471",1726653455,1726653471,0],["450011239",1726653620,1726653531,0],["450011238",1726653695,1726653600,1],["450011234",1726653717,1726653620,1],["450011235",1726653740,1726653641,0],["450011236",1726653788,1726653696,0],["450011237",1726653855,1726653766,0],["450011223",1726653893,1726653806,1],["450011224",1726653926,1726653840,0],["450011225",1726653954,1726653889,0],["450010246",1726653970,1726653901,1],["450024302",1726654020,1726653937,0],["450024092",1726654165,1726654018,0],["450010252",1726654188,1726654044,1],["450011218",1726654221,1726654080,0],["450010250",1726654250,1726654109,1],["450010249",1726654283,1726654142,1],["450011222",1726654312,1726654170,1],["450050044",1726654349,1726654207,0],["450026298",1726654369,1726654222,1],["450012099",1726654448,1726654281,0],["450012098",1726654520,1726654320,0],["450012096",1726654562,1726654440,0],["450012068",1726654635,1726654500,1],["450010514",1726654708,1726654560,0],["450010781",1726654883,1726654680,0],["450014828",1726654912,1726654740,1],["450012864",1726655000,1726654920,1],["450012857",1726655059,1726655040,1],["450025302",1726655088,1726655100,0]],[["450011239",1726747714,1726747131,0],["450011238",1726747827,1726747200,0],["450011234",1726747837,1726747220,1],["450011235",1726747848,1726747241,1],["450011236",1726747876,1726747296,0],["450011237",1726747959,1726747366,0],["450011223",1726748006,1726747406,0],["450011224",1726748029,1726747440,1],["450011225",1726748062,1726747489,0],["450010246",1726748078,1726747501,1],["450024302",1726748126,1726747537,0],["450024092",1726748177,1726747618,0],["450010252",1726748255,1726747644,0],["450011218",1726748277,1726747680,1],["450010250",1726748295,1726747709,1],["450010249",1726748316,1726747742,0],["450011222",1726748337,1726747770,1],["450050044",1726748365,1726747807,0],["450026298",1726748389,1726747822,1],["450012099",1726748481,1726747881,0],["450012098",1726748500,1726747920,1],["450012096",1726748560,1726748040,0],["450012068",1726748611,1726748100,0],["450010514",1726748682,1726748160,0],["450010781",1726748779,1726748280,0],["450014828",1726748851,1726748340,0],["450012864",1726748911,1726748520,0],["450012857",1726749033,1726748640,0],["450025302",1726749095,1726748700,0]],[["450010789",1726745627,1726745446,0],["450012859",1726745704,1726745516,0],["450012093",1726745749,1726745561,0],["450014437",1726745817,1726745586,0],["450014438",1726745843,1726745633,1],["450023941",1726745882,1726745703,0],["450010515",1726746062,1726745760,0],["450012069",1726746134,1726745806,1],["450012097",1726746164,1726745825,0],["450050045",1726746212,1726745880,0],["450012100",1726746263,1726745930,1],["450012801",1726746335,1726746001,0],["450012094",1726746371,1726746022,1],["450011254",1726746395,1726746036,1],["450011221",1726746477,1726746084,0],["450011220",1726746492,1726746105,1],["450011219",1726746518,1726746143,0],["450011218",1726746562,1726746180,1],["450011217",1726746593,1726746205,1],["450011216",1726746625,1726746232,0],["450011215",1726746659,1726746261,1],["450011213",1726746693,1726746290,0],["450010246",1726746813,1726746333,0],["450010247",1726746865,1726746374,0],["450010248",1726746898,1726746409,1],["450010772",1726746931,1726746443,0],["450010773",1726746993,1726746513,0],["450010774",1726747032,1726746569,1],["450011226",1726747057,1726746605,0],["450010775",1726747085,1726746634,0],["450011227",1726747108,1726746657,1],["450011228",1726747150,1726746700,1],["450011229",1726747170,1726746720,0]],[["450012859",1726738584,1726738316,0],["450012093",1726738649,1726738361,0],["450014437",1726738674,1726738386,1],["450014438",1726738720,1726738433,0],["450023941",1726738769,1726738503,0],["450010515",1726738899,1726738560,0],["450012069",1726738955,1726738606,0],["450012097",1726738966,1726738625,1],["450050045",1726738996,1726738680,0],["450012100",1726739085,1726738730,0],["450012801",1726739129,1726738801,0],["450012094",1726739181,1726738822,0],["450011254",1726739195,1726738836,1],["450011221",1726739245,1726738884,0],["450011220",1726739259,1726738905,1],["450011219",1726739284,1726738943,1],["450011218",1726739308,1726738980,0],["450011217",1726739329,1726739005,1],["450011216",1726739352,1726739032,1],["450011215",1726739376,1726739061,0],["450011213",1726739431,1726739090,0],["450010246",1726739483,1726739133,0],["450010247",1726739506,1726739174,1],["450010248",1726739526,1726739209,1],["450010772",1726739545,1726739243,0],["450010773",1726739605,1726739313,0],["450010774",1726739641,1726739369,1],["450011226",1726739664,1726739405,1],["450010775",1726739683,1726739434,0],["450011227",1726739722,1726739457,1],["450011228",1726739795,1726739500,0]],[["450010789",1726752668,1726752646,0],["450012859",1726752702,1726752716,1],["450012093",1726752724,1726752761,0],["450014437",1726752770,1726752786,0],["450014438",1726752819,1726752833,1],["450023941",1726752893,1726752903,0],["450010515",1726752932,1726752960,1],["450012069",1726752963,1726753006,0],["450012097",1726753025,1726753025,0],["450050045",1726753088,1726753080,1],["450012100",1726753146,1726753130,0],["450012801",1726753190,1726753201,0],["450012094",1726753243,1726753222,0],["450011254",1726753261,1726753236,1],["450011221",1726753322,1726753284,0],["450011220",1726753342,1726753305,1],["450011219",1726753378,1726753343,0],["450011218",1726753401,1726753380,1],["450011217",1726753424,1726753417,1],["450011216",1726753450,1726753458,0],["450011215",1726753557,1726753500,0]],[["450011246",1726739838,1726739673,0],["450011248",1726739880,1726739723,1],["450011243",1726739907,1726739756,0],["450011241",1726739947,1726739825,1],["450051471",1726739974,1726739871,0],["450011239",1726740031,1726739931,0],["450011238",1726740098,1726740000,0],["450011234",1726740139,1726740020,0],["450011235",1726740156,1726740041,1],["450011236",1726740202,1726740096,0],["450011237",1726740251,1726740166,1],["450011223",1726740279,1726740206,0],["450011224",1726740302,1726740240,1],["450011225",1726740336,1726740289,0],["450010246",1726740365,1726740301,1],["450024302",1726740451,1726740337,0],["450024092",1726740514,1726740418,0],["450010252",1726740599,1726740444,0],["450011218",1726740625,1726740480,1],["450010250",1726740645,1726740509,1],["450010249",1726740669,1726740542,0],["450011222",1726740683,1726740570,1],["450050044",1726740701,1726740607,0],["450026298",1726740790,1726740622,0],["450012099",1726740851,1726740681,0],["450012098",1726740880,1726740720,1],["450012096",1726740969,1726740840,0],["450012068",1726740991,1726740900,1],["450010514",1726741013,1726740960,0],["450010781",1726741132,1726741080,0],["450014828",1726741149,1726741140,1],["450012864",1726741199,1726741320,0],["450012857",1726741325,1726741440,0],["450025302",1726741415,1726741500,0]],[["450011246",1726833393,1726833273,0],["450011248",1726833456,1726833323,0],["450011243",1726833472,1726833356,1],["450011241",1726833504,1726833425,0],["450051471",1726833527,1726833471,1],["450011239",1726833556,1726833531,0],["450011238",1726833631,1726833600,0],["450011234",1726833659,1726833620,1],["450011235",1726833689,1726833641,0],["450011236",1726833705,1726833696,1],["450011237",1726833726,1726833766,0],["450011223",1726833766,1726833806,1],["450011224",1726833800,1726833840,0],["450011225",1726833870,1726833889,1],["450010246",1726833887,1726833901,1],["450024302",1726833938,1726833937,0],["450024092",1726834036,1726834018,0],["450010252",1726834070,1726834044,1],["450011218",1726834118,1726834080,0],["450010250",1726834146,1726834109,1],["450010249",1726834178,1726834142,0],["450011222",1726834192,1726834170,1],["450050044",1726834211,1726834207,0],["450026298",1726834227,1726834222,1],["450012099",1726834288,1726834281,0],["450012098",1726834359,1726834320,0],["450012096",1726834397,1726834440,0],["450012068",1726834482,1726834500,0],["450010514",1726834540,1726834560,0],["450010781",1726834624,1726834680,0],["450014828",1726834643,1726834740,1],["450012864",1726834701,1726834920,0],["450012857",1726834771,1726835040,0],["450025302",1726835132,1726835100,0]],[["450010789",1726832019,1726831846,0],["450012859",1726832077,1726831916,0],["450012093",1726832115,1726831961,1],["450014437",1726832136,1726831986,0],["450014438",1726832157,1726832033,1],["450023941",1726832189,1726832103,0],["450010515",1726832312,1726832160,0],["450012069",1726832380,1726832206,0],["450012097",1726832423,1726832225,0],["450050045",1726832492,1726832280,1],["450012100",1726832554,1726832330,0],["450012801",1726832594,1726832401,0],["450012094",1726832616,1726832422,1],["450011254",1726832631,1726832436,1],["450011221",1726832682,1726832484,0],["450011220",1726832702,1726832505,1],["450011219",1726832739,1726832543,0],["450011218",1726832775,1726832580,1],["450011217",1726832800,1726832605,0],["450011216",1726832829,1726832632,1],["450011215",1726832860,1726832661,0],["450011213",1726832892,1726832690,0],["450010246",1726833008,1726832733,0],["450010247",1726833093,1726832774,0],["450010248",1726833121,1726832809,1],["450010772",1726833148,1726832843,0],["450010773",1726833208,1726832913,0],["450010774",1726833265,1726832969,1],["450011226",1726833302,1726833005,1],["450010775",1726833331,1726833034,0]],[["450010789",1726824728,1726824646,0],["450012859",1726824756,1726824716,1],["450012093",1726824774,1726824761,0],["450014437",1726824823,1726824786,0],["450014438",1726824854,1726824833,1],["450023941",1726824901,1726824903,0],["450010515",1726824942,1726824960,0],["450012069",1726825017,1726825006,0],["450012097",1726825084,1726825025,0],["450050045",1726825116,1726825080,1],["450012100",1726825145,1726825130,0],["450012801",1726825299,1726825201,0],["450012094",1726825333,1726825222,1],["450011254",1726825356,1726825236,1],["450011221",1726825434,1726825284,0],["450011220",1726825460,1726825305,1],["450011219",1726825508,1726825343,0],["450011218",1726825534,1726825380,1],["450011217",1726825552,1726825405,1],["450011216",1726825571,1726825432,0],["450011215",1726825613,1726825461,0],["450011213",1726825640,1726825490,1],["450010246",1726825679,1726825533,0],["450010247",1726825738,1726825574,0],["450010248",1726825767,1726825609,1],["450010772",1726825795,1726825643,0],["450010773",1726825862,1726825713,0],["450010774",1726825936,1726825769,0],["450011226",1726825961,1726825805,0]],[["450010789",1726839143,1726839046,0],["450012859",1726839172,1726839116,1],["450012093",1726839190,1726839161,0],["450014437",1726839224,1726839186,0],["450014438",1726839304,1726839233,0],["450023941",1726839375,1726839303,1],["450010515",1726839432,1726839360,0],["450012069",1726839480,1726839406,0],["450012097",1726839495,1726839425,1],["450050045",1726839540,1726839480,0],["450012100",1726839615,1726839530,0],["450012801",1726839690,1726839601,0],["450012094",1726839724,1726839622,1],["450011254",1726839747,1726839636,0],["450011221",1726839806,1726839684,0],["450011220",1726839828,1726839705,1],["450011219",1726839867,1726839743,0],["450011218",1726839898,1726839780,1],["450011217",1726839929,1726839817,0],["450011216",1726839958,1726839858,1],["450011215",1726839987,1726839900,0]],[["450011246",1726826207,1726826073,0],["450011248",1726826256,1726826123,1],["450011243",1726826288,1726826156,0],["450011241",1726826341,1726826225,0],["450051471",1726826387,1726826271,1],["450011239",1726826448,1726826331,0],["450011238",1726826527,1726826400,0],["450011234",1726826556,1726826420,1],["450011235",1726826586,1726826441,0],["450011236",1726826639,1726826496,0],["450011237",1726826686,1726826566,1],["450011223",1726826713,1726826606,0],["450011224",1726826731,1726826640,1],["450011225",1726826758,1726826689,1],["450010246",1726826764,1726826701,0],["450024302",1726826913,1726826737,0],["450024092",1726826975,1726826818,0],["450010252",1726826998,1726826844,1],["450011218",1726827030,1726826880,0],["450010250",1726827057,1726826909,1],["450010249",1726827087,1726826942,0],["450011222",1726827142,1726826970,0],["450050044",1726827216,1726827007,0],["450026298",1726827265,1726827022,0],["450012099",1726827330,1726827081,0],["450012098",1726827398,1726827120,0],["450012096",1726827448,1726827240,0],["450012068",1726827518,1726827300,0],["450010514",1726827554,1726827360,0],["450010781",1726827695,1726827480,0],["450014828",1726827737,1726827540,0],["450012864",1726827813,1726827720,0],["450012857",1726827879,1726827840,0],["450025302",1726827990,1726827900,0]],[["450010789",1727083944,1727083846,0],["450012859",1727083988,1727083916,1],["450012093",1727084016,1727083961,0],["450014437",1727084070,1727083986,0],["450014438",1727084125,1727084033,0],["450023941",1727084228,1727084103,1],["450010515",1727084312,1727084160,0],["450012069",1727084379,1727084206,0],["450012097",1727084394,1727084225,1],["450050045",1727084436,1727084280,0],["450012100",1727084499,1727084330,0],["450012801",1727084546,1727084401,0],["450012094",1727084589,1727084422,1],["450011254",1727084617,1727084436,0],["450011221",1727084673,1727084484,0],["450011220",1727084687,1727084505,1],["450011219",1727084711,1727084543,1],["450011218",1727084735,1727084580,0],["450011217",1727084754,1727084605,1],["450011216",1727084774,1727084632,1],["450011215",1727084795,1727084661,0],["450011213",1727084846,1727084690,0],["450010246",1727084893,1727084733,0],["450010247",1727084971,1727084774,0],["450010248",1727085005,1727084809,1],["450010772",1727085038,1727084843,0],["450010773",1727085077,1727084913,0],["450010774",1727085121,1727084969,1],["450011226",1727085150,1727085005,0],["450010775",1727085255,1727085034,1],["450011227",1727085339,1727085057,0]],[["450010789",1727098352,1727098246,0],["450012859",1727098425,1727098316,0],["450012093",1727098466,1727098361,0],["450014437",1727098537,1727098386,0],["450014438",1727098561,1727098433,1],["450023941",1727098596,1727098503,0],["450010515",1727098719,1727098560,0],["450012069",1727098763,1727098606,1],["450012097",1727098781,1727098625,0],["450050045",1727098841,1727098680,0],["450012100",1727098924,1727098730,0],["450012801",1727098997,1727098801,1],["450012094",1727099019,1727098822,0],["450011254",1727099030,1727098836,1],["450011221",1727099066,1727098884,0],["450011220",1727099093,1727098905,1],["450011219",1727099143,1727098943,1],["450011218",1727099191,1727098980,1],["450011217",1727099239,1727099017,0],["450011216",1727099287,1727099058,0]],[["450011246",1727085398,1727085273,0],["450011248",1727085438,1727085323,1],["450011243",1727085464,1727085356,0],["450011241",1727085513,1727085425,0],["450051471",1727085556,1727085471,0],["450011239",1727085637,1727085531,0],["450011238",1727085675,1727085600,0],["450011234",1727085685,1727085620,1],["450011235",1727085696,1727085641,1],["450011236",1727085723,1727085696,1],["450011237",1727085758,1727085766,0],["450011223",1727085814,1727085806,0],["450011224",1727085840,1727085840,1],["450011225",1727085877,1727085889,0],["450010246",1727085892,1727085901,1],["450024302",1727085938,1727085937,0],["450024092",1727085974,1727086018,0],["450010252",1727086005,1727086044,1],["450011218",1727086048,1727086080,0],["450010250",1727086071,1727086109,1],["450010249",1727086097,1727086142,1],["450011222",1727086119,1727086170,0],["450050044",1727086172,1727086207,0],["450026298",1727086184,1727086222,1],["450012099",1727086232,1727086281,0],["450012098",1727086296,1727086320,0],["450012096",1727086359,1727086440,1],["450012068",1727086391,1727086500,0],["450010514",1727086455,1727086560,0],["450010781",1727086586,1727086680,0],["450014828",1727086658,1727086740,0],["450012864",1727086756,1727086920,0]]]}