{"meta":{"id":"949-nan-nan","name":"949 - nan - nan - nan","agency_name":"Bee Network","agency_noc":"BNSM"},"line":{},"stops":{"1800WK01481":{"name":"Selkirk Grove","lon":-2.681699,"lat":53.54454,"bearing":270},"1800WK01331":{"name":"Westfield Community School","lon":-2.670215,"lat":53.542648,"bearing":270},"1800WK23491":{"name":"Baytree Road","lon":-2.652416,"lat":53.558853,"bearing":135},"1800WK06941":{"name":"Pottery Road","lon":-2.639271,"lat":53.54108,"bearing":0},"1800WK00031":{"name":"Worsley Hall Post Office","lon":-2.664801,"lat":53.541924,"bearing":90},"1800WK05661":{"name":"Wigan Pier","lon":-2.641899,"lat":53.542271,"bearing":90},"1800WK06041":{"name":"Worsley Hall Post Office","lon":-2.665053,"lat":53.541641,"bearing":180},"1800WK04061":{"name":"Seven Stars Road","lon":-2.646125,"lat":53.542274,"bearing":90},"1800WK10441":{"name":"Broom Road","lon":-2.668591,"lat":53.540104,"bearing":270},"1800WK09631":{"name":"Peter Street","lon":-2.682312,"lat":53.546028,"bearing":0},"1800WK02891":{"name":"Highfield Community Centre","lon":-2.654166,"lat":53.52253,"bearing":270},"1800WK06131":{"name":"Hope School & College","lon":-2.655848,"lat":53.522053,"bearing":90},"1800WK05391":{"name":"Hunter Road","lon":-2.666274,"lat":53.551155,"bearing":45},"1800WK05501":{"name":"Primrose Grove","lon":-2.663129,"lat":53.543064,"bearing":180},"1800WK01341":{"name":"Montrose School","lon":-2.672767,"lat":53.542732,"bearing":90},"1800WK06491":{"name":"Montrose School","lon":-2.673278,"lat":53.542629,"bearing":270},"1800WK05351":{"name":"Pembroke Road","lon":-2.672029,"lat":53.548561,"bearing":90},"1800WK06151":{"name":"Marus Avenue","lon":-2.649621,"lat":53.52417,"bearing":225},"1800WK05371":{"name":"Harrow Road","lon":-2.668656,"lat":53.550026,"bearing":225},"1800WK04141":{"name":"St Mark's Avenue","lon":-2.65598,"lat":53.542358,"bearing":135},"1800WK01511":{"name":"Marigold Street","lon":-2.666985,"lat":53.540661,"bearing":270},"1800WK05331":{"name":"Comet Road","lon":-2.677393,"lat":53.548016,"bearing":90},"1800WK11071":{"name":"Broom Road","lon":-2.66847,"lat":53.54015,"bearing":90},"1800WK04121":{"name":"Albert Street","lon":-2.652857,"lat":53.540405,"bearing":135},"1800WK04491":{"name":"Peter Street","lon":-2.682176,"lat":53.546032,"bearing":180},"1800WK04131":{"name":"St Mark's Avenue","lon":-2.655856,"lat":53.542133,"bearing":315},"1800WK13281":{"name":"Fire Station","lon":-2.649946,"lat":53.54052,"bearing":225},"1800WK05971":{"name":"Erradale Crescent","lon":-2.666411,"lat":53.520447,"bearing":270},"1800WK13351":{"name":"Riveredge","lon":-2.644022,"lat":53.54092,"bearing":270},"1800WK00451":{"name":"Sherwood Grove","lon":-2.668934,"lat":53.541817,"bearing":0},"1800WK06271":{"name":"Rushdene","lon":-2.643942,"lat":53.529686,"bearing":0},"1800WK06351":{"name":"Park Street","lon":-2.63791,"lat":53.537888,"bearing":0},"1800WK06161":{"name":"St Pauls Avenue","lon":-2.646893,"lat":53.526344,"bearing":45},"1800WK05991":{"name":"Dalton Drive","lon":-2.662579,"lat":53.521358,"bearing":90},"1800WK06121":{"name":"Hope School & College","lon":-2.656477,"lat":53.521763,"bearing":270},"1800WK06321":{"name":"St James Church","lon":-2.637355,"lat":53.536121,"bearing":0},"1800WK03821":{"name":"Falkirk Grove","lon":-2.677808,"lat":53.543736,"bearing":90},"1800WK05961":{"name":"St Aidan's School","lon":-2.669878,"lat":53.522217,"bearing":315},"1800WK12551":{"name":"Britannia Road","lon":-2.680009,"lat":53.548344,"bearing":90},"1800WK08341":{"name":"Blackthorn Avenue","lon":-2.656943,"lat":53.558746,"bearing":90},"1800WK07271":{"name":"Sherwood Grove","lon":-2.668809,"lat":53.541504,"bearing":180},"1800WK02881":{"name":"Warrington Road","lon":-2.651992,"lat":53.523384,"bearing":45},"1800WK05321":{"name":"Comet Road","lon":-2.676833,"lat":53.547932,"bearing":270},"1800WK06001":{"name":"Dalton Drive","lon":-2.661402,"lat":53.521339,"bearing":270},"1800WK04111":{"name":"Albert Street","lon":-2.652642,"lat":53.540192,"bearing":315},"1800WK06931":{"name":"Pottery Road","lon":-2.638937,"lat":53.540947,"bearing":180},"1800WK05361":{"name":"Harrow Road","lon":-2.668823,"lat":53.550072,"bearing":45},"1800WK00091":{"name":"Snowden Avenue","lon":-2.645316,"lat":53.52779,"bearing":225},"1800WK05941":{"name":"Cleveland Avenue","lon":-2.671215,"lat":53.522812,"bearing":90},"1800WK06291":{"name":"Rushdene","lon":-2.643286,"lat":53.53022,"bearing":180},"1800WKH3371":{"name":"St John Fisher RC High School","lon":-2.653188,"lat":53.558048,"bearing":225},"1800WK06331":{"name":"St James Church","lon":-2.637112,"lat":53.536015,"bearing":180},"1800WK05951":{"name":"St Aidan's School","lon":-2.668305,"lat":53.521004,"bearing":135},"1800WK06311":{"name":"Grange Avenue","lon":-2.640335,"lat":53.533569,"bearing":45},"1800WK05451":{"name":"Laurus Mews","lon":-2.658757,"lat":53.544338,"bearing":315},"1800WK00061":{"name":"Primrose Grove","lon":-2.66332,"lat":53.542747,"bearing":0},"1800WK06341":{"name":"Park Street","lon":-2.637774,"lat":53.537907,"bearing":180},"1800WK06171":{"name":"St Pauls Avenue","lon":-2.647649,"lat":53.52544,"bearing":225},"1800WK05341":{"name":"Pembroke Road","lon":-2.672856,"lat":53.548367,"bearing":270},"1800WK05461":{"name":"Laurus Mews","lon":-2.658209,"lat":53.544025,"bearing":135},"1800WK06141":{"name":"Marus Avenue","lon":-2.649772,"lat":53.524235,"bearing":45},"1800WK06301":{"name":"Grange Avenue","lon":-2.640687,"lat":53.532967,"bearing":225},"1800WK05311":{"name":"Smith Avenue","lon":-2.682342,"lat":53.547928,"bearing":180},"1800WK05381":{"name":"Hunter Road","lon":-2.666588,"lat":53.550964,"bearing":225}},"trips":[[["1800WKH3371",1726495838,1726495500],["1800WK05371",1726496270,1726496100],["1800WK05341",1726496386,1726496190],["1800WK05321",1726496452,1726496262],["1800WK05311",1726496576,1726496360],["1800WK04491",1726496642,1726496417],["1800WK03821",1726496697,1726496521],["1800WK01341",1726496809,1726496615],["1800WK07271",1726497070,1726496695],["1800WK11071",1726497180,1726496736],["1800WK00031",1726497314,1726496820],["1800WK00061",1726497429,1726496850],["1800WK05461",1726497526,1726496933],["1800WK04121",1726497643,1726497054],["1800WK05661",1726497759,1726497229],["1800WK06931",1726497825,1726497284],["1800WK06331",1726497947,1726497411],["1800WK06291",1726498070,1726497583],["1800WK00091",1726498130,1726497651],["1800WK06171",1726498190,1726497720],["1800WK02891",1726498253,1726497861],["1800WK06121",1726498383,1726497906],["1800WK05971",1726498436,1726498081],["1800WK05961",1726498494,1726498159]],[["1800WK05381",1726582469,1726582440],["1800WK05371",1726582590,1726582500],["1800WK05341",1726582650,1726582590],["1800WK05321",1726582705,1726582662],["1800WK05311",1726582773,1726582760],["1800WK04491",1726582835,1726582817],["1800WK03821",1726582951,1726582921],["1800WK01341",1726583134,1726583015],["1800WK07271",1726583205,1726583095],["1800WK11071",1726583328,1726583136],["1800WK00031",1726583496,1726583220],["1800WK05461",1726583648,1726583333],["1800WK04141",1726583719,1726583387],["1800WK04121",1726583780,1726583454],["1800WK05661",1726583901,1726583629],["1800WK06931",1726583958,1726583684],["1800WK06341",1726584026,1726583762],["1800WK06331",1726584086,1726583811],["1800WK06301",1726584141,1726583904],["1800WK06291",1726584243,1726583983],["1800WK00091",1726584271,1726584051],["1800WK06171",1726584340,1726584120],["1800WK06151",1726584352,1726584170]],[["1800WKH3371",1726841436,1726841100],["1800WK05381",1726841648,1726841640],["1800WK05371",1726841712,1726841700],["1800WK05321",1726841776,1726841862],["1800WK04491",1726841959,1726842017],["1800WK03821",1726842018,1726842121],["1800WK01341",1726842139,1726842215],["1800WK07271",1726842375,1726842295],["1800WK11071",1726842448,1726842336],["1800WK00031",1726842562,1726842420],["1800WK00061",1726842627,1726842450],["1800WK05461",1726842747,1726842533],["1800WK04141",1726842808,1726842587],["1800WK04121",1726842874,1726842654],["1800WK05661",1726842994,1726842829],["1800WK06931",1726843114,1726842884],["1800WK06341",1726843178,1726842962],["1800WK06331",1726843232,1726843011],["1800WK06301",1726843272,1726843104],["1800WK06291",1726843326,1726843183],["1800WK00091",1726843392,1726843251],["1800WK06171",1726843448,1726843320],["1800WK06151",1726843509,1726843370],["1800WK02891",1726843569,1726843461],["1800WK06001",1726843695,1726843591],["1800WK05971",1726843754,1726843681]],[["1800WKH3371",1727100616,1727100300],["1800WK05381",1727100922,1727100840],["1800WK05341",1727101045,1727100990],["1800WK05321",1727101108,1727101062],["1800WK05311",1727101176,1727101160],["1800WK04491",1727101228,1727101217],["1800WK03821",1727101345,1727101321],["1800WK01341",1727101408,1727101415],["1800WK07271",1727101658,1727101495],["1800WK11071",1727101723,1727101536],["1800WK00031",1727101811,1727101620],["1800WK00061",1727101869,1727101650],["1800WK05461",1727101988,1727101733],["1800WK04141",1727102048,1727101787],["1800WK04121",1727102108,1727101854],["1800WK04061",1727102240,1727101965],["1800WK06931",1727102366,1727102084],["1800WK06301",1727102544,1727102304],["1800WK06291",1727102607,1727102383],["1800WK00091",1727102662,1727102451],["1800WK06171",1727102719,1727102520],["1800WK06121",1727102848,1727102706],["1800WK05971",1727102909,1727102881],["1800WK05961",1727103047,1727102959]],[["1800WK05941",1726466840,1726466826],["1800WK05951",1726466894,1726466834],["1800WK05991",1726466961,1726466845],["1800WK02881",1726467136,1726466866],["1800WK06141",1726467194,1726466871],["1800WK06161",1726467259,1726466880],["1800WK06271",1726467319,1726466945],["1800WK06941",1726467619,1726467164],["1800WK13351",1726467685,1726467213],["1800WK04111",1726467754,1726467303],["1800WK04131",1726468053,1726467350],["1800WK05501",1726468114,1726467448],["1800WK06041",1726468300,1726467480],["1800WK10441",1726468717,1726467555],["1800WK00451",1726468663,1726467604],["1800WK01331",1726468816,1726467636],["1800WK06491",1726468873,1726467688],["1800WK09631",1726469235,1726467886],["1800WK12551",1726469364,1726467992],["1800WK05331",1726469419,1726468038],["1800WK05351",1726469484,1726468130],["1800WK05361",1726469597,1726468200],["1800WK05391",1726469664,1726468260],["1800WK08341",1726469790,1726468860],["1800WK23491",1726469851,1726468980]],[["1800WK05951",1726553300,1726553234],["1800WK05991",1726553355,1726553245],["1800WK06131",1726553426,1726553258],["1800WK02881",1726553486,1726553266],["1800WK06161",1726553544,1726553280],["1800WK06271",1726553610,1726553345],["1800WK06311",1726553667,1726553422],["1800WK13281",1726553909,1726553674],["1800WK04111",1726553970,1726553703],["1800WK04131",1726554092,1726553750],["1800WK05451",1726554135,1726553798],["1800WK06041",1726554290,1726553880],["1800WK01511",1726554428,1726553923],["1800WK10441",1726554489,1726553955],["1800WK00451",1726554547,1726554004],["1800WK01481",1726554970,1726554242],["1800WK09631",1726554916,1726554286],["1800WK12551",1726555040,1726554392],["1800WK05331",1726555103,1726554438],["1800WK05351",1726555167,1726554530],["1800WK05361",1726555221,1726554600],["1800WK23491",1726555526,1726555380]],[["1800WK05941",1726639651,1726639626],["1800WK05951",1726639702,1726639634],["1800WK05991",1726639747,1726639645],["1800WK06131",1726639777,1726639658],["1800WK02881",1726639867,1726639666],["1800WK06311",1726640095,1726639822],["1800WK04111",1726640419,1726640103],["1800WK06041",1726640667,1726640280]],[["1800WK05941",1726726095,1726726026],["1800WK05991",1726726163,1726726045],["1800WK06131",1726726212,1726726058],["1800WK02881",1726726338,1726726066],["1800WK06271",1726726463,1726726145],["1800WK06311",1726726522,1726726222],["1800WK06351",1726726651,1726726307],["1800WK13351",1726726711,1726726413],["1800WK13281",1726726772,1726726474],["1800WK04111",1726726831,1726726503],["1800WK04131",1726726892,1726726550],["1800WK05501",1726727018,1726726648],["1800WK06041",1726727071,1726726680],["1800WK10441",1726727261,1726726755],["1800WK01331",1726727321,1726726836],["1800WK06491",1726727529,1726726888],["1800WK01481",1726727655,1726727042],["1800WK05331",1726727777,1726727238],["1800WK05351",1726727832,1726727330],["1800WK05391",1726727960,1726727460],["1800WK08341",1726728079,1726728060],["1800WK23491",1726728137,1726728180]],[["1800WK05941",1726812446,1726812426],["1800WK05991",1726812517,1726812445],["1800WK06131",1726812578,1726812458],["1800WK02881",1726812636,1726812466],["1800WK06161",1726812757,1726812480],["1800WK06271",1726812796,1726812545],["1800WK06321",1726812973,1726812676],["1800WK13281",1726813160,1726812874],["1800WK04111",1726813214,1726812903],["1800WK04131",1726813275,1726812950],["1800WK05451",1726813402,1726812998],["1800WK05501",1726813517,1726813048],["1800WK06041",1726813639,1726813080],["1800WK00451",1726813768,1726813204],["1800WK01331",1726813831,1726813236],["1800WK01481",1726814067,1726813442],["1800WK05331",1726814195,1726813638],["1800WK05351",1726814260,1726813730],["1800WK05361",1726814318,1726813800],["1800WK05391",1726814376,1726813860],["1800WK08341",1726814497,1726814460],["1800WK23491",1726814531,1726814580]],[["1800WK05951",1727071674,1727071634],["1800WK05991",1727071729,1727071645],["1800WK06131",1727071787,1727071658],["1800WK02881",1727071856,1727071666],["1800WK06161",1727071917,1727071680],["1800WK06271",1727072027,1727071745],["1800WK06311",1727072107,1727071822],["1800WK13351",1727072339,1727072013],["1800WK04111",1727072405,1727072103],["1800WK04131",1727072638,1727072150],["1800WK05451",1727072705,1727072198],["1800WK06041",1727072827,1727072280],["1800WK01511",1727073103,1727072323],["1800WK10441",1727073160,1727072355],["1800WK00451",1727073227,1727072404],["1800WK01331",1727073348,1727072436],["1800WK01481",1727073649,1727072642],["1800WK09631",1727073704,1727072686],["1800WK12551",1727073766,1727072792],["1800WK05351",1727073891,1727072930],["1800WK05361",1727073950,1727073000],["1800WK05391",1727074020,1727073060]]]}