{"meta":{"id":"94a-newcastle-tunstall-biddulph-congleton-2","name":"94A - Newcastle - Congleton (D & G Bus)","agency_name":"D & G Bus","agency_noc":"DAGC","bustimesorg":true},"line":{},"stops":{"3890D057002":{"name":"The Talisman","lon":-2.20665,"lat":53.063831,"bearing":45},"3890D062202":{"name":"Oxford Road","lon":-2.187543,"lat":53.076122,"bearing":225},"0600CO18959":{"name":"Bus Station Alighting Only","lon":-2.211826,"lat":53.16386,"bearing":null},"3800C852802":{"name":"Edgeley Road","lon":-2.16836,"lat":53.110329,"bearing":180},"0600CO234":{"name":"Pet Food Superstore","lon":-2.190134,"lat":53.156166,"bearing":135},"3800C853301":{"name":"James Bateman Middle School","lon":-2.177657,"lat":53.107761,"bearing":90},"3800C801500":{"name":"Church Close","lon":-2.168342,"lat":53.109383,"bearing":180},"3890D050001":{"name":"Furlong Road","lon":-2.211011,"lat":53.061512,"bearing":0},"3800C819301":{"name":"St Lawrence's Church","lon":-2.166189,"lat":53.128319,"bearing":180},"3800C863201":{"name":"Bosley Brook","lon":-2.170366,"lat":53.137733,"bearing":0},"3890D056901":{"name":"Hallfield Grove","lon":-2.204102,"lat":53.064606,"bearing":225},"3800C820102":{"name":"Baileys Bank","lon":-2.168559,"lat":53.134247,"bearing":180},"3890D053702":{"name":"Hallfield Grove","lon":-2.204147,"lat":53.064724,"bearing":45},"3800C820001":{"name":"Broad Oak","lon":-2.171939,"lat":53.146164,"bearing":0},"0600CO227":{"name":"Townsend Road","lon":-2.205507,"lat":53.162453,"bearing":135},"0600CO19023":{"name":"Hulton Close","lon":-2.185355,"lat":53.15424,"bearing":315},"3800C852602":{"name":"Lord Street","lon":-2.169354,"lat":53.112133,"bearing":0},"3800C814901":{"name":"Grange Court","lon":-2.168194,"lat":53.125141,"bearing":45},"3890D062701":{"name":"New Black Bull","lon":-2.181403,"lat":53.08931,"bearing":0},"3800C893201":{"name":"High Street","lon":-2.177901,"lat":53.116371,"bearing":270},"3890D062102":{"name":"Biddulph Road","lon":-2.189809,"lat":53.075527,"bearing":225},"3800C853302":{"name":"James Bateman Middle School","lon":-2.178852,"lat":53.107704,"bearing":270},"3890D057102":{"name":"Medical Centre","lon":-2.210374,"lat":53.062439,"bearing":45},"3890D062901":{"name":"Working Men's Club","lon":-2.196238,"lat":53.071289,"bearing":225},"0600CO229":{"name":"Highcroft Avenue","lon":-2.19908,"lat":53.160213,"bearing":315},"3800C863102":{"name":"Childerplay Road","lon":-2.180931,"lat":53.094238,"bearing":180},"3800C509801":{"name":"Morris Square","lon":-2.217051,"lat":53.031399,"bearing":180},"3800C801400":{"name":"Woodland Street","lon":-2.173951,"lat":53.107571,"bearing":90},"3800C509800":{"name":"Morris Square","lon":-2.216764,"lat":53.030689,"bearing":0},"3890D062601":{"name":"Fisher Street","lon":-2.18168,"lat":53.087646,"bearing":0},"3800C825801":{"name":"Bemersley Road","lon":-2.181596,"lat":53.092602,"bearing":180},"3800C818401":{"name":"South View","lon":-2.176137,"lat":53.11599,"bearing":0},"3890D002601":{"name":"stop A","lon":-2.210521,"lat":53.059025,"bearing":0},"3890D051602":{"name":"Brownhills High School","lon":-2.210392,"lat":53.050789,"bearing":180},"3890D051601":{"name":"Brownhills High School","lon":-2.210662,"lat":53.051113,"bearing":0},"3890D061902":{"name":"Fegg Hayes Road","lon":-2.193407,"lat":53.072437,"bearing":225},"3890D002602":{"name":"stop B","lon":-2.210402,"lat":53.059105,"bearing":180},"3800C817401":{"name":"Coronation Avenue","lon":-2.180508,"lat":53.103867,"bearing":0},"3800C518802":{"name":"Grange Lane","lon":-2.214916,"lat":53.027832,"bearing":180},"0600CO260":{"name":"Mossley Corner","lon":-2.181346,"lat":53.150265,"bearing":135},"3890D062902":{"name":"Working Men's Club","lon":-2.196209,"lat":53.071415,"bearing":45},"3800C817402":{"name":"Coronation Avenue","lon":-2.180301,"lat":53.104233,"bearing":180},"3890D057101":{"name":"Medical Centre","lon":-2.209435,"lat":53.062649,"bearing":225},"3890D050002":{"name":"Furlong Road","lon":-2.210786,"lat":53.061405,"bearing":180},"3800C852401":{"name":"Mayfield Road","lon":-2.172354,"lat":53.107815,"bearing":0},"3890D062101":{"name":"Biddulph Road","lon":-2.189064,"lat":53.075806,"bearing":45},"3890D052401":{"name":"Station Street","lon":-2.214337,"lat":53.043251,"bearing":0},"3890D056702":{"name":"Benson Street","lon":-2.200211,"lat":53.068768,"bearing":45},"3800C592402":{"name":"Sidmouth Avenue","lon":-2.223169,"lat":53.015007,"bearing":225},"3890D027302":{"name":"Furlong Tavern","lon":-2.201958,"lat":53.065781,"bearing":0},"3800C850001":{"name":"Brown Lees Road","lon":-2.180423,"lat":53.097672,"bearing":0},"3800C591802":{"name":"Second Avenue","lon":-2.221359,"lat":53.036945,"bearing":225},"3800C850901":{"name":"Brown Lees Industrial Estate","lon":-2.180537,"lat":53.099911,"bearing":180},"3800C503101":{"name":"Marsh Avenue","lon":-2.22027,"lat":53.033829,"bearing":135},"0600CO232":{"name":"Railway Station","lon":-2.194151,"lat":53.158146,"bearing":315},"3890D027301":{"name":"Furlong Tavern","lon":-2.201824,"lat":53.065742,"bearing":225},"3800C503602":{"name":"Sandy Lane","lon":-2.220104,"lat":53.018906,"bearing":45},"3890D062301":{"name":"Hollington Drive","lon":-2.184778,"lat":53.078888,"bearing":45},"3800C820002":{"name":"Broad Oak","lon":-2.17173,"lat":53.146145,"bearing":180},"3800C864192":{"name":"Briarswood","lon":-2.171569,"lat":53.120743,"bearing":225},"3800C851501":{"name":"Princess Street","lon":-2.171842,"lat":53.114197,"bearing":90},"3890D051701":{"name":"Brownhills Business Park","lon":-2.210701,"lat":53.052956,"bearing":0},"0600CO19022":{"name":"Roseville Drive","lon":-2.183703,"lat":53.152447,"bearing":315},"3800C510100":{"name":"Bus Station","lon":-2.224697,"lat":53.010681,"bearing":null},"3890D062501":{"name":"Peck Mill Lane","lon":-2.181387,"lat":53.085354,"bearing":0},"3800C850902":{"name":"Brown Lees Industrial Estate","lon":-2.180733,"lat":53.100376,"bearing":0},"3890D056602":{"name":"Colley Road","lon":-2.199382,"lat":53.070126,"bearing":0},"3800C852402":{"name":"Mayfield Road","lon":-2.172219,"lat":53.107624,"bearing":180},"3890D057001":{"name":"Clanway Street","lon":-2.207528,"lat":53.063335,"bearing":225},"3800C592201":{"name":"May Avenue","lon":-2.217781,"lat":53.022442,"bearing":225},"3800C509601":{"name":"St Margaret's Church","lon":-2.215834,"lat":53.029438,"bearing":0},"3890D062302":{"name":"Hollington Drive","lon":-2.185148,"lat":53.078121,"bearing":225},"3890D051702":{"name":"Brownhills Business Park","lon":-2.210565,"lat":53.052757,"bearing":180},"3890D056701":{"name":"Benson Street","lon":-2.200254,"lat":53.068424,"bearing":180},"0600CO230":{"name":"Highcroft Avenue","lon":-2.199515,"lat":53.160439,"bearing":135},"3800C864191":{"name":"Briarswood","lon":-2.172271,"lat":53.120731,"bearing":45},"3800C506501":{"name":"St Andrew's Church","lon":-2.222112,"lat":53.035397,"bearing":180},"3800C506500":{"name":"St Andrew's Church","lon":-2.222502,"lat":53.035782,"bearing":0},"3800C592502":{"name":"Hanover Street","lon":-2.223804,"lat":53.013748,"bearing":180},"3800C591801":{"name":"Second Avenue","lon":-2.219382,"lat":53.038017,"bearing":45},"0600CO261":{"name":"Roseville Drive","lon":-2.183013,"lat":53.152096,"bearing":135},"3890D062702":{"name":"New Black Bull","lon":-2.181195,"lat":53.089447,"bearing":180},"3890D051802":{"name":"White Horse","lon":-2.210395,"lat":53.054493,"bearing":180},"3890D002701":{"name":"Woodland Street","lon":-2.210302,"lat":53.056911,"bearing":180},"3800C816800":{"name":"Fire Station","lon":-2.170567,"lat":53.113014,"bearing":315},"0600CO235":{"name":"Pet Food Superstore","lon":-2.190747,"lat":53.156227,"bearing":315},"0600CO216":{"name":"Town Hall","lon":-2.210505,"lat":53.162846,"bearing":90},"3800C892101":{"name":"Mayfield Road","lon":-2.16832,"lat":53.107586,"bearing":180},"3800C850002":{"name":"Brown Lees Road","lon":-2.180123,"lat":53.097492,"bearing":180},"3800C851701":{"name":"Well Street","lon":-2.171527,"lat":53.113956,"bearing":0},"3890D062502":{"name":"Peck Mill Lane","lon":-2.181222,"lat":53.085339,"bearing":180},"3800C851301":{"name":"John Street","lon":-2.175998,"lat":53.114944,"bearing":270},"3800C801201":{"name":"Kingsfield Road","lon":-2.173934,"lat":53.114365,"bearing":315},"3800C509600":{"name":"St Margaret's Church","lon":-2.21582,"lat":53.029774,"bearing":180},"3800C503601":{"name":"Sandy Lane","lon":-2.218889,"lat":53.020435,"bearing":225},"3890D051202":{"name":"Longport Road","lon":-2.214092,"lat":53.041973,"bearing":180},"3800C592302":{"name":"Newcastle Museum and Art Gallery","lon":-2.221284,"lat":53.016468,"bearing":225},"3800C592501":{"name":"Hannover Street","lon":-2.223924,"lat":53.013908,"bearing":0},"0600CO231":{"name":"The Parklands","lon":-2.195743,"lat":53.159763,"bearing":135},"3890D051201":{"name":"Longport Road","lon":-2.214418,"lat":53.041603,"bearing":0},"0600CO259":{"name":"Mossley Corner","lon":-2.181329,"lat":53.149925,"bearing":315},"0600CO217":{"name":"Mountbatten Way","lon":-2.207348,"lat":53.162628,"bearing":90},"3800C592301":{"name":"Newcastle Museum and Art Gallery","lon":-2.221019,"lat":53.017117,"bearing":45},"3800C592202":{"name":"May Avenue","lon":-2.218093,"lat":53.022182,"bearing":45},"3890D062602":{"name":"Finch Street","lon":-2.181544,"lat":53.08717,"bearing":180},"3800C814902":{"name":"Grange Court","lon":-2.167867,"lat":53.125431,"bearing":180},"3800C819001":{"name":"Grange Road","lon":-2.166091,"lat":53.12999,"bearing":0},"3800C500901":{"name":"Upper Marsh","lon":-2.216362,"lat":53.024719,"bearing":225},"3890D056601":{"name":"Colley Road","lon":-2.19886,"lat":53.070236,"bearing":225},"3800C597602":{"name":"Vale View","lon":-2.216553,"lat":53.039112,"bearing":225},"3800C503102":{"name":"Marsh Avenue","lon":-2.219489,"lat":53.032776,"bearing":315},"3800C597601":{"name":"Vale View","lon":-2.216585,"lat":53.039406,"bearing":45},"3800C592401":{"name":"Sidmouth Avenue","lon":-2.223185,"lat":53.015259,"bearing":45},"0600CO19015":{"name":"Castle Inn PH","lon":-2.175329,"lat":53.14872,"bearing":135},"3800C815900":{"name":"High Street","lon":-2.17605,"lat":53.116779,"bearing":90},"3800C518801":{"name":"Grange Lane","lon":-2.215257,"lat":53.027401,"bearing":0},"0600CO000086":{"name":"Henshall Hall Drive","lon":-2.187692,"lat":53.155201,"bearing":315},"3800C852801":{"name":"Edgeley Road","lon":-2.168494,"lat":53.110184,"bearing":0},"3800C851302":{"name":"John Street","lon":-2.174817,"lat":53.114742,"bearing":90},"3800C863101":{"name":"Childerplay Road","lon":-2.181333,"lat":53.093948,"bearing":0},"3890D051402":{"name":"Trubshaw Cross","lon":-2.211501,"lat":53.045753,"bearing":225},"3800C863202":{"name":"Bosley Brook","lon":-2.169839,"lat":53.136772,"bearing":180},"3890D051401":{"name":"Trubshaw Cross","lon":-2.211428,"lat":53.046265,"bearing":0},"3890D062201":{"name":"Oxford Road","lon":-2.186592,"lat":53.077087,"bearing":45},"3800C852601":{"name":"Lord Street","lon":-2.169279,"lat":53.112232,"bearing":180},"3890D051501":{"name":"Brereton Place","lon":-2.209953,"lat":53.049629,"bearing":0},"3800C801401":{"name":"Woodland Street","lon":-2.174205,"lat":53.107506,"bearing":270},"3890D062001":{"name":"Biddulph Road","lon":-2.19185,"lat":53.07476,"bearing":45},"3890D002801":{"name":"Highgate","lon":-2.210597,"lat":53.05611,"bearing":0},"0600CO19016":{"name":"Castle Inn PH","lon":-2.174699,"lat":53.14817,"bearing":315},"0600CO228":{"name":"Townsend Road","lon":-2.205327,"lat":53.162254,"bearing":315},"3800C817101":{"name":"The Barley Mow PH","lon":-2.168663,"lat":53.111244,"bearing":0},"3800C820101":{"name":"Baileys Bank","lon":-2.168933,"lat":53.134426,"bearing":0},"3800C892102":{"name":"Mayfield Road","lon":-2.16847,"lat":53.107719,"bearing":0},"3890D051502":{"name":"Westport Lake Road","lon":-2.210023,"lat":53.04858,"bearing":225},"0600CO253":{"name":"Hulton Close","lon":-2.185311,"lat":53.154392,"bearing":135},"0600CO233":{"name":"Railway Station","lon":-2.193462,"lat":53.157879,"bearing":135},"3800C817100":{"name":"The Barley Mow PH","lon":-2.168483,"lat":53.110985,"bearing":180},"3890D062002":{"name":"Biddulph Road","lon":-2.191954,"lat":53.074478,"bearing":225},"3890D051302":{"name":"Trubshaw Cross","lon":-2.212525,"lat":53.044834,"bearing":225},"3800C500900":{"name":"Upper Marsh","lon":-2.216378,"lat":53.025116,"bearing":45},"3890D061901":{"name":"Fegg Hayes Road","lon":-2.193245,"lat":53.07275,"bearing":45}},"trips":[[["3800C592501",1726471148,1726470954,0],["3800C592401",1726471174,1726470978,1],["3800C592301",1726471217,1726471017,0],["3800C503602",1726471255,1726471049,1],["3800C592202",1726471326,1726471108,0],["3800C500900",1726471687,1726471161,0],["3800C518801",1726471891,1726471202,1],["3800C509601",1726472066,1726471237,0],["3800C509800",1726472075,1726471260,1],["3800C503102",1726472106,1726471340,0],["3800C506500",1726472191,1726471446,0],["3800C591801",1726472249,1726471534,0],["3800C597601",1726472306,1726471599,0],["3890D051201",1726472432,1726471676,0],["3890D052401",1726472443,1726471726,1],["3890D051401",1726472466,1726471831,0],["3890D051501",1726472511,1726471935,1],["3890D051601",1726472532,1726471982,1],["3890D051701",1726472556,1726472037,0],["3890D002801",1726472581,1726472132,1],["3890D002601",1726472605,1726472220,0],["3890D050001",1726472660,1726472284,0],["3890D057102",1726472737,1726472309,0],["3890D057002",1726472778,1726472376,0],["3890D053702",1726472844,1726472421,0],["3890D027302",1726472863,1726472464,1],["3890D056702",1726472899,1726472545,0],["3890D056602",1726472974,1726472581,0],["3890D062902",1726473028,1726472640,0],["3890D061901",1726473060,1726472668,1],["3890D062001",1726473091,1726472695,0],["3890D062101",1726473115,1726472720,1],["3890D062201",1726473137,1726472744,1],["3890D062301",1726473162,1726472770,0],["3890D062501",1726473218,1726472855,0],["3890D062601",1726473256,1726472884,1],["3890D062701",1726473283,1726472904,0],["3800C863101",1726473311,1726472962,1],["3800C850001",1726473333,1726473009,0],["3800C850902",1726473361,1726473043,1],["3800C817401",1726473397,1726473087,0],["3800C853301",1726473461,1726473140,0],["3800C801400",1726473608,1726473168,0],["3800C852401",1726473614,1726473180,1],["3800C892102",1726473659,1726473269,0],["3800C852801",1726473733,1726473363,0],["3800C817101",1726473787,1726473404,0],["3800C852602",1726473852,1726473441,0],["3800C816800",1726473913,1726473485,0],["3800C851701",1726473939,1726473527,1],["3800C801201",1726473975,1726473585,0],["3800C851301",1726474012,1726473637,1],["3800C818401",1726474041,1726473677,0],["3800C893201",1726474092,1726473720,1],["3800C864191",1726474218,1726473825,0],["3800C814901",1726474275,1726473922,0],["3800C819001",1726474297,1726474017,1],["3800C820101",1726474319,1726474108,0],["3800C863201",1726474339,1726474173,1],["3800C820001",1726474388,1726474335,0],["0600CO19016",1726474464,1726474385,0],["0600CO259",1726474501,1726474468,1],["0600CO19022",1726474525,1726474523,0],["0600CO19023",1726474545,1726474563,1],["0600CO000086",1726474561,1726474595,1],["0600CO235",1726474581,1726474635,0],["0600CO232",1726474618,1726474689,0],["0600CO229",1726474661,1726474758,1],["0600CO228",1726474711,1726474839,0]],[["3800C592501",1726557402,1726557354,0],["3800C592401",1726557436,1726557378,1],["3800C592301",1726557490,1726557417,0],["3800C503602",1726557514,1726557449,1],["3800C592202",1726557558,1726557508,1],["3800C500900",1726557597,1726557561,0],["3800C518801",1726557682,1726557602,0],["3800C509601",1726557776,1726557637,0],["3800C509800",1726557784,1726557660,1],["3800C503102",1726557813,1726557740,1],["3800C506500",1726557851,1726557846,0],["3800C591801",1726557935,1726557934,0],["3800C597601",1726557980,1726557999,1],["3890D051201",1726558034,1726558076,0],["3890D052401",1726558118,1726558126,0],["3890D051401",1726558154,1726558231,1],["3890D051501",1726558189,1726558335,0],["3890D051601",1726558257,1726558382,0],["3890D051701",1726558271,1726558437,1],["3890D002801",1726558295,1726558532,1],["3890D002601",1726558317,1726558620,0],["3890D050001",1726558607,1726558684,0],["3890D057102",1726558674,1726558709,0],["3890D057002",1726558705,1726558776,1],["3890D053702",1726558725,1726558821,1],["3890D027302",1726558745,1726558864,0],["3890D056702",1726558798,1726558945,0],["3890D056602",1726558846,1726558981,1],["3890D062902",1726558925,1726559040,0],["3890D061901",1726558988,1726559068,0],["3890D062001",1726559046,1726559095,0],["3890D062101",1726559069,1726559120,1],["3890D062201",1726559091,1726559144,1],["3890D062301",1726559115,1726559170,0],["3890D062501",1726559154,1726559255,0],["3890D062601",1726559200,1726559284,0],["3890D062701",1726559228,1726559304,1],["3800C863101",1726559308,1726559362,0],["3800C850001",1726559337,1726559409,1],["3800C850902",1726559357,1726559443,1],["3800C817401",1726559384,1726559487,0],["3800C853301",1726559508,1726559540,0],["3800C801400",1726559616,1726559568,0],["3800C852401",1726559675,1726559580,0],["3800C892102",1726559734,1726559669,0],["3800C852801",1726559800,1726559763,0],["3800C817101",1726559859,1726559804,0],["3800C852602",1726559918,1726559841,0],["3800C816800",1726559939,1726559885,1],["3800C851701",1726559959,1726559927,1],["3800C801201",1726559987,1726559985,0],["3800C851301",1726560025,1726560037,0],["3800C818401",1726560064,1726560077,1],["3800C893201",1726560106,1726560120,0],["3800C864191",1726560201,1726560225,0],["3800C814901",1726560275,1726560322,0],["3800C819001",1726560317,1726560417,1],["3800C820101",1726560358,1726560508,0],["3800C863201",1726560375,1726560573,1],["3800C820001",1726560418,1726560735,0],["0600CO19016",1726560477,1726560785,0],["0600CO259",1726560509,1726560868,1],["0600CO19022",1726560531,1726560923,0],["0600CO19023",1726560569,1726560963,1],["0600CO000086",1726560599,1726560995,0],["0600CO235",1726560612,1726561035,1],["0600CO232",1726560628,1726561089,1],["0600CO229",1726560650,1726561158,0],["0600CO228",1726560710,1726561239,0],["0600CO18959",1726560799,1726561320,0]],[["3800C592501",1726643738,1726643754,0],["3800C592401",1726643781,1726643778,0],["3800C592301",1726643830,1726643817,0],["3800C503602",1726643847,1726643849,0],["3800C592202",1726643922,1726643908,0],["3800C500900",1726644129,1726643961,0],["3800C518801",1726644267,1726644002,0],["3800C509601",1726644298,1726644037,1],["3800C509800",1726644319,1726644060,0],["3800C503102",1726644393,1726644140,0],["3800C506500",1726644445,1726644246,0],["3800C591801",1726644484,1726644334,0],["3800C597601",1726644543,1726644399,1],["3890D051201",1726644613,1726644476,0],["3890D052401",1726644649,1726644526,0],["3890D051401",1726644709,1726644631,0],["3890D051501",1726644746,1726644735,0],["3890D051601",1726644791,1726644782,0],["3890D051701",1726644809,1726644837,1],["3890D002801",1726644839,1726644932,0],["3890D002601",1726644872,1726645020,0],["3890D050001",1726645003,1726645084,0],["3890D057102",1726645057,1726645109,0],["3890D057002",1726645083,1726645176,1],["3890D053702",1726645101,1726645221,0],["3890D027302",1726645113,1726645264,1],["3890D056702",1726645137,1726645345,0],["3890D056602",1726645189,1726645381,0],["3890D062902",1726645241,1726645440,0],["3890D061901",1726645411,1726645468,0],["3890D062001",1726645474,1726645495,0],["3890D062101",1726645501,1726645520,0],["3890D062201",1726645525,1726645544,1],["3890D062301",1726645551,1726645570,0],["3890D062501",1726645632,1726645655,1],["3890D062601",1726645660,1726645684,0],["3890D062701",1726645671,1726645704,1],["3800C863101",1726645704,1726645762,1],["3800C850001",1726645731,1726645809,0],["3800C850902",1726645755,1726645843,1],["3800C817401",1726645787,1726645887,0],["3800C853301",1726645848,1726645940,0],["3800C801400",1726645981,1726645968,0],["3800C852401",1726645991,1726645980,1],["3800C892102",1726646068,1726646069,0],["3800C852801",1726646129,1726646163,0],["3800C817101",1726646165,1726646204,1],["3800C852602",1726646198,1726646241,0],["3800C816800",1726646243,1726646285,0],["3800C851701",1726646261,1726646327,1],["3800C801201",1726646287,1726646385,0],["3800C851301",1726646328,1726646437,1],["3800C818401",1726646359,1726646477,0],["3800C893201",1726646473,1726646520,0],["3800C864191",1726646530,1726646625,0],["3800C814901",1726646614,1726646722,0],["3800C819001",1726646651,1726646817,1],["3800C820101",1726646686,1726646908,0],["3800C863201",1726646706,1726646973,1],["3800C820001",1726646756,1726647135,0],["0600CO19016",1726646788,1726647185,1],["0600CO259",1726646841,1726647268,0],["0600CO19022",1726646880,1726647323,1],["0600CO19023",1726646908,1726647363,0],["0600CO000086",1726646930,1726647395,1],["0600CO235",1726646957,1726647435,0],["0600CO232",1726646989,1726647489,1],["0600CO229",1726647029,1726647558,0],["0600CO228",1726647085,1726647639,0],["0600CO18959",1726647174,1726647720,0]],[["3800C592501",1726730101,1726730154,0],["3800C592401",1726730151,1726730178,0],["3800C592301",1726730205,1726730217,0],["3800C503602",1726730223,1726730249,0],["3800C592202",1726730302,1726730308,1],["3800C500900",1726730373,1726730361,0],["3800C518801",1726730472,1726730402,0],["3800C509601",1726730491,1726730437,1],["3800C509800",1726730503,1726730460,1],["3800C503102",1726730546,1726730540,0],["3800C506500",1726730677,1726730646,1],["3800C591801",1726730786,1726730734,0],["3800C597601",1726730867,1726730799,0],["3890D051201",1726730975,1726730876,0],["3890D052401",1726730996,1726730926,1],["3890D051401",1726731039,1726731031,0],["3890D051501",1726731106,1726731135,0],["3890D051601",1726731136,1726731182,0],["3890D051701",1726731169,1726731237,1],["3890D002801",1726731226,1726731332,0],["3890D002601",1726731394,1726731420,1],["3890D050001",1726731516,1726731484,0],["3890D057102",1726731583,1726731509,0],["3890D057002",1726731618,1726731576,1],["3890D053702",1726731641,1726731621,1],["3890D027302",1726731663,1726731664,0],["3890D056702",1726731722,1726731745,0],["3890D056602",1726731738,1726731781,1],["3890D062902",1726731764,1726731840,0],["3890D061901",1726731834,1726731868,0],["3890D062001",1726731895,1726731895,0],["3890D062101",1726731915,1726731920,1],["3890D062201",1726731934,1726731944,0],["3890D062301",1726731951,1726731970,1],["3890D062501",1726732006,1726732055,0],["3890D062601",1726732077,1726732084,0],["3890D062701",1726732090,1726732104,1],["3800C863101",1726732126,1726732162,0],["3800C850001",1726732205,1726732209,0],["3800C850902",1726732257,1726732243,0],["3800C817401",1726732300,1726732287,0],["3800C853301",1726732372,1726732340,0],["3800C801400",1726732504,1726732368,0],["3800C852401",1726732573,1726732380,0],["3800C892102",1726732624,1726732469,0],["3800C852801",1726732661,1726732563,1],["3800C817101",1726732677,1726732604,1],["3800C852602",1726732692,1726732641,0],["3800C816800",1726732712,1726732685,1],["3800C851701",1726732730,1726732727,1],["3800C801201",1726732756,1726732785,0],["3800C851301",1726732786,1726732837,0],["3800C818401",1726732848,1726732877,0],["3800C893201",1726732908,1726732920,0],["3800C864191",1726732975,1726733025,0],["3800C814901",1726733049,1726733122,0],["3800C819001",1726733115,1726733217,0],["3800C820101",1726733143,1726733308,1],["3800C863201",1726733163,1726733373,0],["3800C820001",1726733219,1726733535,0],["0600CO19016",1726733238,1726733585,1],["0600CO259",1726733270,1726733668,0],["0600CO19022",1726733309,1726733723,1],["0600CO19023",1726733337,1726733763,1],["0600CO000086",1726733360,1726733795,0],["0600CO235",1726733381,1726733835,1],["0600CO232",1726733410,1726733889,0],["0600CO229",1726733475,1726733958,0],["0600CO228",1726733515,1726734039,0],["0600CO18959",1726733645,1726734120,0]],[["3800C592501",1726816625,1726816554,0],["3800C592401",1726816683,1726816578,0],["3800C592301",1726816715,1726816617,1],["3800C503602",1726816742,1726816649,0],["3800C592202",1726816790,1726816708,0],["3800C500900",1726816909,1726816761,0],["3800C518801",1726816985,1726816802,0],["3800C509601",1726817025,1726816837,1],["3800C509800",1726817052,1726816860,0],["3800C503102",1726817087,1726816940,0],["3800C506500",1726817173,1726817046,0],["3800C591801",1726817216,1726817134,1],["3800C597601",1726817247,1726817199,0],["3890D051201",1726817372,1726817276,0],["3890D052401",1726817395,1726817326,1],["3890D051401",1726817442,1726817431,0],["3890D051501",1726817489,1726817535,0],["3890D051601",1726817505,1726817582,1],["3890D051701",1726817524,1726817637,1],["3890D002801",1726817556,1726817732,0],["3890D002601",1726817629,1726817820,0],["3890D050001",1726817867,1726817884,0],["3890D057102",1726817931,1726817909,0],["3890D057002",1726817966,1726817976,1],["3890D053702",1726817989,1726818021,0],["3890D027302",1726818001,1726818064,1],["3890D056702",1726818025,1726818145,0],["3890D056602",1726818055,1726818181,1],["3890D062902",1726818104,1726818240,0],["3890D061901",1726818166,1726818268,0],["3890D062001",1726818229,1726818295,0],["3890D062101",1726818249,1726818320,1],["3890D062201",1726818268,1726818344,1],["3890D062301",1726818288,1726818370,0],["3890D062501",1726818353,1726818455,0],["3890D062601",1726818410,1726818484,0],["3890D062701",1726818426,1726818504,1],["3800C863101",1726818471,1726818562,0],["3800C850001",1726818505,1726818609,1],["3800C850902",1726818529,1726818643,0],["3800C817401",1726818613,1726818687,1],["3800C853301",1726818714,1726818740,0],["3800C801400",1726818774,1726818768,0],["3800C852401",1726818781,1726818780,1],["3800C892102",1726818830,1726818869,0],["3800C852801",1726818887,1726818963,0],["3800C817101",1726818911,1726819004,1],["3800C852602",1726818932,1726819041,1],["3800C816800",1726818958,1726819085,0],["3800C851701",1726819000,1726819127,1],["3800C801201",1726819058,1726819185,1],["3800C851301",1726819110,1726819237,0],["3800C818401",1726819179,1726819277,1],["3800C893201",1726819254,1726819320,0],["3800C864191",1726819319,1726819425,0],["3800C814901",1726819378,1726819522,0],["3800C819001",1726819429,1726819617,0],["3800C820101",1726819476,1726819708,1],["3800C863201",1726819509,1726819773,0],["3800C820001",1726819564,1726819935,0],["0600CO19016",1726819584,1726819985,1],["0600CO259",1726819616,1726820068,0],["0600CO19022",1726819689,1726820123,0],["0600CO19023",1726819702,1726820163,1],["0600CO000086",1726819713,1726820195,1],["0600CO235",1726819727,1726820235,1],["0600CO232",1726819745,1726820289,0],["0600CO229",1726819800,1726820358,1],["0600CO228",1726819864,1726820439,0],["0600CO18959",1726819921,1726820520,0]],[["3800C592501",1727075749,1727075754,0],["3800C592401",1727075775,1727075778,1],["3800C592301",1727075816,1727075817,0],["3800C503602",1727075838,1727075849,1],["3800C592202",1727075878,1727075908,0],["3800C500900",1727075956,1727075961,0],["3800C518801",1727076004,1727076002,0],["3800C509601",1727076075,1727076037,0],["3800C509800",1727076086,1727076060,1],["3800C503102",1727076124,1727076140,0],["3800C506500",1727076254,1727076246,0],["3800C591801",1727076338,1727076334,0],["3800C597601",1727076398,1727076399,0],["3890D051201",1727076462,1727076476,0],["3890D052401",1727076528,1727076526,0],["3890D051401",1727076554,1727076631,1],["3890D051501",1727076580,1727076735,0],["3890D051601",1727076611,1727076782,1],["3890D051701",1727076647,1727076837,0],["3890D002801",1727076704,1727076932,0],["3890D002601",1727076776,1727077020,0],["3890D050001",1727077074,1727077084,0],["3890D057102",1727077086,1727077109,1],["3890D057002",1727077118,1727077176,0],["3890D053702",1727077136,1727077221,1],["3890D027302",1727077152,1727077264,1],["3890D056702",1727077184,1727077345,0],["3890D056602",1727077250,1727077381,0],["3890D062902",1727077372,1727077440,0],["3890D061901",1727077403,1727077468,1],["3890D062001",1727077433,1727077495,0],["3890D062101",1727077463,1727077520,1],["3890D062201",1727077492,1727077544,0],["3890D062301",1727077566,1727077570,0],["3890D062501",1727077596,1727077655,0],["3890D062601",1727077646,1727077684,1],["3890D062701",1727077681,1727077704,0],["3800C863101",1727077807,1727077762,0],["3800C850001",1727077840,1727077809,1],["3800C850902",1727077864,1727077843,0],["3800C817401",1727077918,1727077887,1],["3800C853301",1727077984,1727077940,0],["3800C801400",1727078049,1727077968,0],["3800C852401",1727078080,1727077980,0],["3800C892102",1727078122,1727078069,1],["3800C852801",1727078167,1727078163,0],["3800C817101",1727078213,1727078204,0],["3800C852602",1727078236,1727078241,1],["3800C816800",1727078262,1727078285,1],["3800C851701",1727078288,1727078327,0],["3800C801201",1727078319,1727078385,1],["3800C851301",1727078346,1727078437,0],["3800C818401",1727078382,1727078477,0],["3800C893201",1727078422,1727078520,1],["3800C864191",1727078519,1727078625,0],["3800C814901",1727078570,1727078722,0],["3800C819001",1727078648,1727078817,0],["3800C820101",1727078678,1727078908,1],["3800C863201",1727078699,1727078973,0],["3800C820001",1727078759,1727079135,0],["0600CO19016",1727078779,1727079185,1],["0600CO259",1727078811,1727079268,0],["0600CO19022",1727078847,1727079323,1],["0600CO19023",1727078873,1727079363,0],["0600CO000086",1727078893,1727079395,1],["0600CO235",1727078918,1727079435,1],["0600CO232",1727078952,1727079489,0],["0600CO229",1727079026,1727079558,1],["0600CO228",1727079112,1727079639,1],["0600CO18959",1727079199,1727079720,0]],[["3800C592501",1726466734,1726466754,0],["3800C592401",1726466915,1726466778,0],["3800C592301",1726466957,1726466817,0],["3800C503602",1726466975,1726466849,1],["3800C592202",1726467009,1726466908,1],["3800C500900",1726467040,1726466961,0],["3800C518801",1726467074,1726467002,0],["3800C509601",1726467096,1726467037,1],["3800C509800",1726467110,1726467060,1],["3800C503102",1726467159,1726467140,0],["3800C506500",1726467211,1726467246,1],["3800C591801",1726467255,1726467334,0],["3800C597601",1726467285,1726467399,1],["3890D051201",1726467322,1726467476,1],["3890D052401",1726467345,1726467526,0],["3890D051401",1726467388,1726467631,0],["3890D051501",1726467444,1726467735,1],["3890D051601",1726467469,1726467782,0],["3890D051701",1726467477,1726467837,1],["3890D002801",1726467490,1726467932,0],["3890D002601",1726467546,1726468020,0],["3890D050001",1726468007,1726468084,0],["3890D057102",1726468099,1726468109,0],["3890D057002",1726468134,1726468176,1],["3890D053702",1726468157,1726468221,0],["3890D027302",1726468180,1726468264,1],["3890D056702",1726468223,1726468345,0],["3890D056602",1726468257,1726468381,0],["3890D062902",1726468403,1726468440,0],["3890D061901",1726468451,1726468468,0],["3890D062001",1726468524,1726468495,0],["3890D062101",1726468554,1726468520,1],["3890D062201",1726468582,1726468544,0],["3890D062301",1726468596,1726468570,1],["3890D062501",1726468641,1726468655,0],["3890D062601",1726468688,1726468684,0],["3890D062701",1726468706,1726468704,1],["3800C863101",1726468758,1726468762,0],["3800C850001",1726468821,1726468809,0],["3800C850902",1726468836,1726468843,1],["3800C817401",1726468856,1726468887,1],["3800C853301",1726468879,1726468940,0],["3800C801400",1726468945,1726468968,0],["3800C852401",1726469008,1726468980,0],["3800C892102",1726469067,1726469069,1],["3800C852801",1726469130,1726469163,1],["3800C817101",1726469157,1726469204,0],["3800C852602",1726469182,1726469241,1],["3800C816800",1726469211,1726469285,1],["3800C851701",1726469239,1726469327,1],["3800C801201",1726469278,1726469385,1],["3800C851301",1726469313,1726469437,0],["3800C818401",1726469413,1726469477,0],["3800C893201",1726469479,1726469520,0],["3800C864191",1726469593,1726469625,0],["3800C814901",1726469668,1726469722,0],["3800C819001",1726469726,1726469817,0],["3800C820101",1726469796,1726469908,0],["3800C863201",1726469805,1726469973,1],["3800C820001",1726469828,1726470135,0],["0600CO19016",1726469858,1726470185,1],["0600CO259",1726469909,1726470268,0],["0600CO19022",1726469948,1726470323,1],["0600CO19023",1726469977,1726470363,0],["0600CO000086",1726470003,1726470395,1],["0600CO235",1726470035,1726470435,0],["0600CO232",1726470062,1726470489,1],["0600CO229",1726470096,1726470558,0],["0600CO228",1726470156,1726470639,0],["0600CO18959",1726470277,1726470720,0]],[["3800C592202",1726553380,1726553308,0],["3800C500900",1726553437,1726553361,0],["3800C518801",1726553465,1726553402,1],["3800C509601",1726553488,1726553437,1],["3800C509800",1726553504,1726553460,0],["3800C503102",1726553519,1726553540,1],["3800C506500",1726553539,1726553646,0],["3800C591801",1726553616,1726553734,0],["3800C597601",1726553641,1726553799,1],["3890D051201",1726553670,1726553876,0],["3890D052401",1726553713,1726553926,0],["3890D051401",1726553743,1726554031,1],["3890D051501",1726553772,1726554135,0],["3890D051601",1726553791,1726554182,1],["3890D051701",1726553813,1726554237,1],["3890D002801",1726553851,1726554332,1],["3890D002601",1726553886,1726554420,0],["3890D050001",1726554432,1726554484,0],["3890D057102",1726554449,1726554509,1],["3890D057002",1726554495,1726554576,0],["3890D053702",1726554535,1726554621,0],["3890D027302",1726554565,1726554664,1],["3890D056702",1726554621,1726554745,0],["3890D056602",1726554657,1726554781,0],["3890D062902",1726554848,1726554840,0],["3890D061901",1726554888,1726554868,1],["3890D062001",1726554927,1726554895,0],["3890D062101",1726554955,1726554920,1],["3890D062201",1726554981,1726554944,0],["3890D062301",1726555029,1726554970,0],["3890D062501",1726555091,1726555055,0],["3890D062601",1726555109,1726555084,1],["3890D062701",1726555122,1726555104,1],["3800C863101",1726555159,1726555162,0],["3800C850001",1726555232,1726555209,0],["3800C850902",1726555254,1726555243,1],["3800C817401",1726555283,1726555287,0],["3800C853301",1726555345,1726555340,0],["3800C801400",1726555395,1726555368,1],["3800C852401",1726555416,1726555380,0],["3800C892102",1726555470,1726555469,0],["3800C852801",1726555505,1726555563,1],["3800C817101",1726555520,1726555604,0],["3800C852602",1726555592,1726555641,0],["3800C816800",1726555811,1726555685,1],["3800C851701",1726556021,1726555727,0],["3800C801201",1726556028,1726555785,1],["3800C851301",1726556034,1726555837,1],["3800C818401",1726556039,1726555877,1],["3800C893201",1726556044,1726555920,1],["3800C864191",1726556056,1726556025,1],["3800C814901",1726556068,1726556122,0],["3800C819001",1726556114,1726556217,0],["3800C820101",1726556161,1726556308,1],["3800C863201",1726556194,1726556373,0],["3800C820001",1726556254,1726556535,0],["0600CO19016",1726556274,1726556585,1],["0600CO259",1726556306,1726556668,0],["0600CO19022",1726556346,1726556723,1],["0600CO19023",1726556375,1726556763,0],["0600CO000086",1726556403,1726556795,1],["0600CO235",1726556439,1726556835,0],["0600CO232",1726556470,1726556889,0],["0600CO229",1726556544,1726556958,1],["0600CO228",1726556630,1726557039,0],["0600CO18959",1726556741,1726557120,0]],[["3800C592501",1726639670,1726639554,0],["3800C592401",1726639688,1726639578,1],["3800C592301",1726639717,1726639617,0],["3800C503602",1726639738,1726639649,1],["3800C592202",1726639777,1726639708,1],["3800C500900",1726639812,1726639761,0],["3800C518801",1726639846,1726639802,1],["3800C509601",1726639875,1726639837,0],["3800C509800",1726639903,1726639860,0],["3800C503102",1726639917,1726639940,0],["3800C506500",1726639970,1726640046,0],["3800C591801",1726640017,1726640134,0],["3800C597601",1726640049,1726640199,0],["3890D051201",1726640113,1726640276,1],["3890D052401",1726640154,1726640326,1],["3890D051401",1726640241,1726640431,1],["3890D051501",1726640328,1726640535,1],["3890D051601",1726640367,1726640582,1],["3890D051701",1726640412,1726640637,1],["3890D002801",1726640491,1726640732,1],["3890D002601",1726640564,1726640820,0],["3890D050001",1726640844,1726640884,0],["3890D057102",1726640865,1726640909,1],["3890D057002",1726640922,1726640976,0],["3890D053702",1726640958,1726641021,1],["3890D027302",1726640992,1726641064,0],["3890D056702",1726641047,1726641145,0],["3890D056602",1726641108,1726641181,1],["3890D062902",1726641209,1726641240,0],["3890D061901",1726641262,1726641268,0],["3890D062001",1726641315,1726641295,0],["3890D062101",1726641345,1726641320,1],["3890D062201",1726641374,1726641344,1],["3890D062301",1726641405,1726641370,0],["3890D062501",1726641490,1726641455,0],["3890D062601",1726641509,1726641484,0],["3890D062701",1726641519,1726641504,1],["3800C863101",1726641548,1726641562,0],["3800C850001",1726641625,1726641609,1],["3800C850902",1726641681,1726641643,0],["3800C817401",1726641729,1726641687,0],["3800C853301",1726641792,1726641740,0],["3800C801400",1726641914,1726641768,0],["3800C852401",1726641933,1726641780,0],["3800C892102",1726641987,1726641869,0],["3800C852801",1726642023,1726641963,0],["3800C817101",1726642069,1726642004,0],["3800C852602",1726642081,1726642041,0],["3800C816800",1726642115,1726642085,1],["3800C851701",1726642147,1726642127,1],["3800C801201",1726642191,1726642185,1],["3800C851301",1726642231,1726642237,1],["3800C818401",1726642262,1726642277,1],["3800C893201",1726642295,1726642320,1],["3800C864191",1726642375,1726642425,1],["3800C814901",1726642450,1726642522,1],["3800C819001",1726642523,1726642617,1],["3800C820101",1726642592,1726642708,1],["3800C863201",1726642642,1726642773,1],["3800C820001",1726642766,1726642935,1],["0600CO19016",1726642805,1726642985,1],["0600CO259",1726642868,1726643068,1],["0600CO19022",1726642911,1726643123,1],["0600CO19023",1726642941,1726643163,1],["0600CO000086",1726642966,1726643195,1],["0600CO235",1726642996,1726643235,1],["0600CO232",1726643038,1726643289,1],["0600CO229",1726643091,1726643358,1],["0600CO228",1726643153,1726643439,1],["0600CO18959",1726643215,1726643520,0]],[["3800C592401",1727071737,1727071578,0],["3800C592301",1727071773,1727071617,1],["3800C503602",1727071802,1727071649,0],["3800C592202",1727071830,1727071708,1],["3800C500900",1727071855,1727071761,0],["3800C518801",1727071892,1727071802,1],["3800C509601",1727071924,1727071837,0],["3800C509800",1727071934,1727071860,1],["3800C503102",1727071968,1727071940,0],["3800C506500",1727071998,1727072046,0],["3800C591801",1727072135,1727072134,0],["3800C597601",1727072175,1727072199,1],["3890D051201",1727072222,1727072276,0],["3890D052401",1727072254,1727072326,1],["3890D051401",1727072320,1727072431,0],["3890D051501",1727072330,1727072535,0],["3890D051601",1727072350,1727072582,1],["3890D051701",1727072373,1727072637,1],["3890D002801",1727072412,1727072732,1],["3890D002601",1727072449,1727072820,0],["3890D050001",1727072890,1727072884,0],["3890D057102",1727072943,1727072909,0],["3890D057002",1727072976,1727072976,1],["3890D053702",1727072999,1727073021,0],["3890D027302",1727073042,1727073064,1],["3890D056702",1727073124,1727073145,0],["3890D056602",1727073151,1727073181,1],["3890D062902",1727073194,1727073240,0],["3890D061901",1727073331,1727073268,0],["3890D062001",1727073406,1727073295,0],["3890D062101",1727073438,1727073320,1],["3890D062201",1727073469,1727073344,0],["3890D062301",1727073494,1727073370,1],["3890D062501",1727073576,1727073455,0],["3890D062601",1727073595,1727073484,1],["3890D062701",1727073608,1727073504,1],["3800C863101",1727073645,1727073562,0],["3800C850001",1727073700,1727073609,0],["3800C850902",1727073764,1727073643,0],["3800C817401",1727073790,1727073687,1],["3800C853301",1727073822,1727073740,0],["3800C801400",1727074007,1727073768,0],["3800C852401",1727074013,1727073780,1],["3800C892102",1727074059,1727073869,0],["3800C852801",1727074122,1727073963,0],["3800C817101",1727074182,1727074004,0],["3800C852602",1727074216,1727074041,1],["3800C816800",1727074257,1727074085,0],["3800C851701",1727074281,1727074127,1],["3800C801201",1727074315,1727074185,0],["3800C851301",1727074371,1727074237,0],["3800C818401",1727074412,1727074277,0],["3800C893201",1727074469,1727074320,1],["3800C864191",1727074609,1727074425,0],["3800C814901",1727074675,1727074522,0],["3800C819001",1727074737,1727074617,0],["3800C820101",1727074775,1727074708,0],["3800C863201",1727074796,1727074773,1],["3800C820001",1727074850,1727074935,0],["0600CO19016",1727074916,1727074985,0],["0600CO259",1727074970,1727075068,0],["0600CO19022",1727075022,1727075123,1],["0600CO19023",1727075060,1727075163,0],["0600CO000086",1727075070,1727075195,1],["0600CO235",1727075083,1727075235,0],["0600CO232",1727075133,1727075289,0],["0600CO229",1727075256,1727075358,0],["0600CO228",1727075459,1727075439,0],["0600CO18959",1727075809,1727075520,0]],[["0600CO216",1726504225,1726503916,0],["0600CO217",1726504271,1726503944,0],["0600CO227",1726504326,1726503960,0],["0600CO230",1726504364,1726504020,1],["0600CO231",1726504385,1726504054,0],["0600CO233",1726504418,1726504088,1],["0600CO234",1726504455,1726504126,0],["0600CO253",1726504510,1726504175,0],["0600CO261",1726504526,1726504213,1],["0600CO260",1726504540,1726504244,1],["0600CO19015",1726504564,1726504300,0],["3800C820002",1726504580,1726504349,1],["3800C863202",1726504626,1726504485,0],["3800C820102",1726504694,1726504523,0],["3800C819301",1726504712,1726504612,0],["3800C814902",1726504750,1726504656,1],["3800C864192",1726504816,1726504731,0],["3800C815900",1726504939,1726504800,0],["3800C851302",1726505047,1726504886,0],["3800C851501",1726505112,1726504960,0],["3800C852601",1726505165,1726505059,0],["3800C817100",1726505241,1726505112,0],["3800C852802",1726505252,1726505138,1],["3800C801500",1726505268,1726505176,1],["3800C892101",1726505299,1726505247,0],["3800C852402",1726505364,1726505340,0],["3800C801401",1726505381,1726505355,1],["3800C853302",1726505421,1726505389,0],["3800C817402",1726505476,1726505433,0],["3800C850901",1726505578,1726505486,0],["3800C850002",1726505665,1726505516,0],["3800C863102",1726505707,1726505556,1],["3800C825801",1726505729,1726505577,0],["3890D062702",1726505757,1726505615,1],["3890D062602",1726505777,1726505643,0],["3890D062502",1726505791,1726505666,1],["3890D062302",1726505846,1726505759,0],["3890D062202",1726505906,1726505789,0],["3890D062102",1726505923,1726505807,1],["3890D062002",1726505942,1726505828,1],["3890D061902",1726505967,1726505855,0],["3890D062901",1726506016,1726505880,0],["3890D056601",1726506087,1726505930,0],["3890D056701",1726506104,1726505982,1],["3890D027301",1726506129,1726506056,0],["3890D056901",1726506161,1726506103,1],["3890D057001",1726506203,1726506166,0],["3890D057101",1726506234,1726506201,1],["3890D050002",1726506268,1726506240,0],["3890D002602",1726506337,1726506300,0],["3890D002701",1726506387,1726506347,0],["3890D051802",1726506446,1726506398,0],["3890D051702",1726506512,1726506435,0],["3890D051602",1726506531,1726506477,1],["3890D051502",1726506553,1726506524,1],["3890D051402",1726506582,1726506587,0],["3890D051302",1726506592,1726506610,1],["3890D051202",1726506620,1726506674,0],["3800C597602",1726506657,1726506742,1],["3800C591802",1726506698,1726506819,0],["3800C506501",1726506757,1726506853,0],["3800C503101",1726506777,1726506894,1],["3800C509801",1726506809,1726506960,0],["3800C509600",1726506871,1726506989,0],["3800C518802",1726507009,1726507022,0],["3800C500901",1726507075,1726507075,0],["3800C592201",1726507118,1726507114,1],["3800C503601",1726507157,1726507149,0],["3800C592302",1726507213,1726507218,0],["3800C592402",1726507237,1726507248,1],["3800C592502",1726507254,1726507269,1],["3800C510100",1726507294,1726507320,0]],[["0600CO217",1726590383,1726590344,0],["0600CO227",1726590397,1726590360,1],["0600CO230",1726590450,1726590420,1],["0600CO231",1726590479,1726590454,1],["0600CO233",1726590509,1726590488,0],["0600CO234",1726590535,1726590526,1],["0600CO253",1726590569,1726590575,1],["0600CO261",1726590595,1726590613,1],["0600CO260",1726590616,1726590644,1],["0600CO19015",1726590655,1726590700,0],["3800C820002",1726590713,1726590749,0],["3800C863202",1726590751,1726590885,0],["3800C820102",1726590778,1726590923,1],["3800C819301",1726590843,1726591012,1],["3800C814902",1726590875,1726591056,1],["3800C864192",1726590929,1726591131,0],["3800C815900",1726591040,1726591200,0],["3800C851302",1726591227,1726591286,0],["3800C851501",1726591275,1726591360,1],["3800C852601",1726591340,1726591459,0],["3800C817100",1726591399,1726591512,0],["3800C852802",1726591410,1726591538,0],["3800C801500",1726591431,1726591576,1],["3800C892101",1726591470,1726591647,1],["3800C852402",1726591522,1726591740,0],["3800C801401",1726591667,1726591755,0],["3800C853302",1726591761,1726591789,0],["3800C817402",1726591847,1726591833,0],["3800C850901",1726591937,1726591886,1],["3800C850002",1726591988,1726591916,0],["3800C863102",1726592021,1726591956,1],["3800C825801",1726592039,1726591977,1],["3890D062702",1726592070,1726592015,1],["3890D062602",1726592094,1726592043,1],["3890D062502",1726592113,1726592066,0],["3890D062302",1726592184,1726592159,0],["3890D062202",1726592231,1726592189,1],["3890D062102",1726592259,1726592207,1],["3890D062002",1726592292,1726592228,0],["3890D061902",1726592330,1726592255,1],["3890D062901",1726592366,1726592280,0],["3890D056601",1726592395,1726592330,1],["3890D056701",1726592426,1726592382,1],["3890D027301",1726592469,1726592456,0],["3890D056901",1726592491,1726592503,1],["3890D057001",1726592521,1726592566,0],["3890D057101",1726592535,1726592601,0],["3890D050002",1726592582,1726592640,1],["3890D002602",1726592654,1726592700,0],["3890D002701",1726592683,1726592747,1],["3890D051802",1726592715,1726592798,0],["3890D051702",1726592745,1726592835,1],["3890D051602",1726592779,1726592877,1],["3890D051502",1726592817,1726592924,1],["3890D051402",1726592867,1726592987,1],["3890D051302",1726592886,1726593010,0],["3890D051202",1726592944,1726593074,0],["3800C597602",1726592984,1726593142,1],["3800C591802",1726593029,1726593219,1],["3800C506501",1726593049,1726593253,0],["3800C503101",1726593096,1726593294,0],["3800C509801",1726593242,1726593360,0],["3800C509600",1726593318,1726593389,0],["3800C518802",1726593412,1726593422,0],["3800C500901",1726593444,1726593475,0],["3800C592201",1726593504,1726593514,0],["3800C503601",1726593524,1726593549,1],["3800C592302",1726593565,1726593618,1],["3800C592402",1726593582,1726593648,1],["3800C592502",1726593594,1726593669,1],["3800C510100",1726593624,1726593720,0]],[["3800C863202",1726677047,1726677285,0],["3800C820102",1726677064,1726677323,1],["3800C819301",1726677105,1726677412,0],["3800C814902",1726677146,1726677456,1],["3800C864192",1726677216,1726677531,0],["3800C815900",1726677285,1726677600,0],["3800C851302",1726677579,1726677686,0],["3800C851501",1726677633,1726677760,0],["3800C852601",1726677697,1726677859,0],["3800C817100",1726677735,1726677912,0],["3800C852802",1726677743,1726677938,1],["3800C801500",1726677753,1726677976,1],["3800C892101",1726677774,1726678047,0],["3800C852402",1726677869,1726678140,0],["3800C801401",1726678110,1726678155,0],["3800C853302",1726678155,1726678189,1],["3800C817402",1726678213,1726678233,0],["3800C850901",1726678298,1726678286,0],["3800C850002",1726678317,1726678316,1],["3800C863102",1726678343,1726678356,1],["3800C825801",1726678357,1726678377,0],["3890D062702",1726678393,1726678415,1],["3890D062602",1726678420,1726678443,0],["3890D062502",1726678431,1726678466,1],["3890D062302",1726678475,1726678559,0],["3890D062202",1726678534,1726678589,0],["3890D062102",1726678548,1726678607,1],["3890D062002",1726678565,1726678628,1],["3890D061902",1726678586,1726678655,0],["3890D062901",1726678601,1726678680,1],["3890D056601",1726678631,1726678730,1],["3890D056701",1726678662,1726678782,0],["3890D027301",1726678698,1726678856,1],["3890D056901",1726678721,1726678903,0],["3890D057001",1726678758,1726678966,0],["3890D057101",1726678794,1726679001,1],["3890D050002",1726678834,1726679040,0],["3890D002602",1726678967,1726679100,0],["3890D002701",1726679068,1726679147,0],["3890D051802",1726679157,1726679198,0],["3890D051702",1726679188,1726679235,0],["3890D051602",1726679206,1726679277,1],["3890D051502",1726679226,1726679324,0],["3890D051402",1726679260,1726679387,1],["3890D051302",1726679272,1726679410,1],["3890D051202",1726679306,1726679474,0],["3800C597602",1726679346,1726679542,1],["3800C591802",1726679391,1726679619,1],["3800C506501",1726679411,1726679653,0],["3800C503101",1726679437,1726679694,1],["3800C509801",1726679479,1726679760,0],["3800C509600",1726679507,1726679789,1],["3800C518802",1726679538,1726679822,0],["3800C500901",1726679613,1726679875,0],["3800C592201",1726679673,1726679914,1],["3800C503601",1726679727,1726679949,0],["3800C592302",1726679766,1726680018,1],["3800C592402",1726679783,1726680048,0],["3800C592502",1726679804,1726680069,1],["3800C510100",1726679854,1726680120,0]],[["0600CO230",1727108862,1727108820,0],["0600CO231",1727108947,1727108854,0],["0600CO233",1727108973,1727108888,1],["0600CO234",1727109003,1727108926,0],["0600CO253",1727109050,1727108975,0],["0600CO261",1727109123,1727109013,0],["0600CO260",1727109143,1727109044,1],["0600CO19015",1727109180,1727109100,0],["3800C820002",1727109208,1727109149,1],["3800C863202",1727109287,1727109285,1],["3800C820102",1727109309,1727109323,1],["3800C819301",1727109361,1727109412,0],["3800C814902",1727109420,1727109456,0],["3800C864192",1727109492,1727109531,0],["3800C815900",1727109534,1727109600,0],["3800C851302",1727109679,1727109686,0],["3800C851501",1727109737,1727109760,1],["3800C852601",1727109814,1727109859,0],["3800C817100",1727109831,1727109912,1],["3800C852802",1727109840,1727109938,1],["3800C801500",1727109853,1727109976,1],["3800C892101",1727109876,1727110047,0],["3800C852402",1727109948,1727110140,0],["3800C801401",1727110111,1727110155,0],["3800C853302",1727110158,1727110189,1],["3800C817402",1727110219,1727110233,0],["3800C850901",1727110287,1727110286,0],["3800C850002",1727110321,1727110316,1],["3800C863102",1727110367,1727110356,0],["3800C825801",1727110382,1727110377,1],["3890D062702",1727110410,1727110415,1],["3890D062602",1727110430,1727110443,0],["3890D062502",1727110450,1727110466,1],["3890D062302",1727110532,1727110559,0],["3890D062202",1727110593,1727110589,0],["3890D062102",1727110613,1727110607,1],["3890D062002",1727110637,1727110628,1],["3890D061902",1727110667,1727110655,0],["3890D062901",1727110687,1727110680,1],["3890D056601",1727110728,1727110730,0],["3890D056701",1727110754,1727110782,1],["3890D027301",1727110790,1727110856,0],["3890D056901",1727110811,1727110903,1],["3890D057001",1727110839,1727110966,1],["3890D057101",1727110854,1727111001,0],["3890D050002",1727110894,1727111040,1],["3890D002602",1727110955,1727111100,0],["3890D002701",1727111079,1727111147,0],["3890D051802",1727111159,1727111198,0],["3890D051702",1727111174,1727111235,1],["3890D051602",1727111192,1727111277,1],["3890D051502",1727111211,1727111324,0],["3890D051402",1727111238,1727111387,1],["3890D051302",1727111248,1727111410,1],["3890D051202",1727111276,1727111474,0],["3800C597602",1727111344,1727111542,0],["3800C591802",1727111379,1727111619,0],["3800C506501",1727111459,1727111653,0],["3800C503101",1727111502,1727111694,1],["3800C509801",1727111570,1727111760,0],["3800C509600",1727111631,1727111789,1],["3800C518802",1727111701,1727111822,0],["3800C500901",1727111738,1727111875,1],["3800C592201",1727111765,1727111914,0],["3800C503601",1727111780,1727111949,1],["3800C592302",1727111810,1727112018,0],["3800C592402",1727111856,1727112048,1],["3800C592502",1727111888,1727112069,0],["3800C510100",1727111941,1727112120,0]],[["3800C592501",1726726051,1726725954,0],["3800C592401",1726726069,1726725978,1],["3800C592301",1726726099,1726726017,0],["3800C503602",1726726119,1726726049,1],["3800C592202",1726726156,1726726108,0],["3800C500900",1726726229,1726726161,0],["3800C518801",1726726265,1726726202,1],["3800C509601",1726726296,1726726237,0],["3800C509800",1726726309,1726726260,1],["3800C503102",1726726354,1726726340,0],["3800C506500",1726726381,1726726446,1],["3800C591801",1726726403,1726726534,0],["3800C597601",1726726475,1726726599,0],["3890D051201",1726726538,1726726676,0],["3890D052401",1726726555,1726726726,1],["3890D051401",1726726592,1726726831,0],["3890D051501",1726726639,1726726935,0],["3890D051601",1726726660,1726726982,1],["3890D051701",1726726684,1726727037,1],["3890D002801",1726726725,1726727132,0],["3890D002601",1726726758,1726727220,0],["3890D050001",1726727248,1726727284,0],["3890D057102",1726727273,1726727309,1],["3890D057002",1726727339,1726727376,0],["3890D053702",1726727378,1726727421,1],["3890D027302",1726727415,1726727464,0],["3890D056702",1726727466,1726727545,0],["3890D056602",1726727531,1726727581,1],["3890D062902",1726727638,1726727640,0],["3890D061901",1726727679,1726727668,1],["3890D062001",1726727719,1726727695,0],["3890D062101",1726727744,1726727720,1],["3890D062201",1726727768,1726727744,0],["3890D062301",1726727818,1726727770,0],["3890D062501",1726727880,1726727855,1],["3890D062601",1726727901,1726727884,1],["3890D062701",1726727915,1726727904,1],["3800C863101",1726727957,1726727962,0],["3800C850001",1726728002,1726728009,0],["3800C850902",1726728038,1726728043,1],["3800C817401",1726728084,1726728087,0],["3800C853301",1726728117,1726728140,0],["3800C801400",1726728257,1726728168,0],["3800C852401",1726728314,1726728180,0],["3800C892102",1726728344,1726728269,1],["3800C852801",1726728376,1726728363,0],["3800C817101",1726728506,1726728404,0],["3800C852602",1726728521,1726728441,1],["3800C816800",1726728539,1726728485,1],["3800C851701",1726728556,1726728527,0],["3800C801201",1726728591,1726728585,1],["3800C851301",1726728623,1726728637,0],["3800C818401",1726728663,1726728677,0],["3800C893201",1726728725,1726728720,0],["3800C864191",1726728785,1726728825,0],["3800C814901",1726728873,1726728922,0],["3800C819001",1726728932,1726729017,0],["3800C820101",1726728970,1726729108,0],["3800C863201",1726728992,1726729173,1],["3800C820001",1726729046,1726729335,0],["0600CO19016",1726729111,1726729385,0],["0600CO259",1726729168,1726729468,0],["0600CO19022",1726729203,1726729523,1],["0600CO19023",1726729229,1726729563,0],["0600CO000086",1726729253,1726729595,1],["0600CO235",1726729282,1726729635,0],["0600CO232",1726729336,1726729689,0],["0600CO229",1726729389,1726729758,1],["0600CO228",1726729451,1726729839,0],["0600CO18959",1726729585,1726729920,0]],[["0600CO216",1726763047,1726763116,0],["0600CO217",1726763103,1726763144,0],["0600CO227",1726763122,1726763160,1],["0600CO230",1726763195,1726763220,0],["0600CO231",1726763213,1726763254,1],["0600CO233",1726763230,1726763288,1],["0600CO234",1726763250,1726763326,1],["0600CO253",1726763275,1726763375,0],["0600CO261",1726763307,1726763413,1],["0600CO260",1726763334,1726763444,1],["0600CO19015",1726763381,1726763500,0],["3800C820002",1726763398,1726763549,1],["3800C863202",1726763445,1726763685,0],["3800C820102",1726763477,1726763723,1],["3800C819301",1726763553,1726763812,0],["3800C814902",1726763579,1726763856,1],["3800C864192",1726763622,1726763931,0],["3800C815900",1726763665,1726764000,0],["3800C851302",1726763990,1726764086,0],["3800C851501",1726764052,1726764160,0],["3800C852601",1726764149,1726764259,0],["3800C817100",1726764177,1726764312,1],["3800C852802",1726764191,1726764338,1],["3800C801500",1726764211,1726764376,0],["3800C892101",1726764263,1726764447,1],["3800C852402",1726764332,1726764540,0],["3800C801401",1726764463,1726764555,0],["3800C853302",1726764540,1726764589,0],["3800C817402",1726764586,1726764633,0],["3800C850901",1726764638,1726764686,0],["3800C850002",1726764712,1726764716,0],["3800C863102",1726764736,1726764756,1],["3800C825801",1726764748,1726764777,1],["3890D062702",1726764771,1726764815,0],["3890D062602",1726764811,1726764843,1],["3890D062502",1726764843,1726764866,0],["3890D062302",1726764887,1726764959,0],["3890D062202",1726764937,1726764989,0],["3890D062102",1726764959,1726765007,1],["3890D062002",1726764984,1726765028,1],["3890D061902",1726765016,1726765055,0],["3890D062901",1726765080,1726765080,0],["3890D056601",1726765114,1726765130,0],["3890D056701",1726765149,1726765182,1],["3890D027301",1726765199,1726765256,0],["3890D056901",1726765219,1726765303,1],["3890D057001",1726765247,1726765366,1],["3890D057101",1726765262,1726765401,0],["3890D050002",1726765316,1726765440,1],["3890D002602",1726765398,1726765500,0],["3890D002701",1726765439,1726765547,1],["3890D051802",1726765484,1726765598,1],["3890D051702",1726765516,1726765635,1],["3890D051602",1726765552,1726765677,1],["3890D051502",1726765594,1726765724,1],["3890D051402",1726765649,1726765787,1],["3890D051302",1726765669,1726765810,1],["3890D051202",1726765724,1726765874,1],["3800C597602",1726765784,1726765942,1],["3800C591802",1726765851,1726766019,0],["3800C506501",1726765864,1726766053,0],["3800C503101",1726765932,1726766094,0],["3800C509801",1726765947,1726766160,0],["3800C509600",1726765988,1726766189,0],["3800C518802",1726766029,1726766222,0],["3800C500901",1726766060,1726766275,1],["3800C592201",1726766083,1726766314,0],["3800C503601",1726766124,1726766349,0],["3800C592302",1726766176,1726766418,1],["3800C592402",1726766199,1726766448,1],["3800C592502",1726766215,1726766469,1],["3800C510100",1726766253,1726766520,0]],[["3800C592301",1726813645,1726812417,0],["3800C503602",1726813646,1726812449,1],["3800C592202",1726813647,1726812508,1],["3800C500900",1726813648,1726812561,1],["3800C518801",1726813649,1726812602,1],["3800C509601",1726813650,1726812637,1],["3800C509800",1726813650,1726812660,1],["3800C503102",1726813652,1726812740,1],["3800C506500",1726813654,1726812846,1],["3800C591801",1726813656,1726812934,1],["3800C597601",1726813658,1726812999,1],["3890D051201",1726813660,1726813076,1],["3890D052401",1726813661,1726813126,1],["3890D051401",1726813663,1726813231,1],["3890D051501",1726813665,1726813335,1],["3890D051601",1726813666,1726813382,1],["3890D051701",1726813668,1726813437,1],["3890D002801",1726813670,1726813532,1],["3890D002601",1726813672,1726813620,1],["3890D050001",1726813673,1726813684,0],["3890D057102",1726813703,1726813709,1],["3890D057002",1726813785,1726813776,1],["3890D053702",1726813839,1726813821,1],["3890D027302",1726813891,1726813864,1],["3890D056702",1726813990,1726813945,1],["3890D056602",1726814033,1726813981,1],["3890D062902",1726814105,1726814040,1],["3890D061901",1726814139,1726814068,1],["3890D062001",1726814172,1726814095,1],["3890D062101",1726814202,1726814120,1],["3890D062201",1726814231,1726814144,1],["3890D062301",1726814263,1726814170,1],["3890D062501",1726814366,1726814255,1],["3890D062601",1726814401,1726814284,1],["3890D062701",1726814426,1726814304,1],["3800C863101",1726814496,1726814362,1],["3800C850001",1726814553,1726814409,1],["3800C850902",1726814594,1726814443,1],["3800C817401",1726814648,1726814487,1],["3800C853301",1726814712,1726814540,1],["3800C801400",1726814746,1726814568,0],["3800C852401",1726814822,1726814580,0],["3800C892102",1726814885,1726814669,0],["3800C852801",1726814961,1726814763,0],["3800C817101",1726814982,1726814804,1],["3800C852602",1726815001,1726814841,0],["3800C816800",1726815029,1726814885,1],["3800C851701",1726815055,1726814927,0],["3800C801201",1726815096,1726814985,1],["3800C851301",1726815132,1726815037,0],["3800C818401",1726815180,1726815077,0],["3800C893201",1726815269,1726815120,1],["3800C864191",1726815488,1726815225,0],["3800C814901",1726815589,1726815322,0],["3800C819001",1726815617,1726815417,1],["3800C820101",1726815644,1726815508,0],["3800C863201",1726815712,1726815573,0],["3800C820001",1726815752,1726815735,0],["0600CO19016",1726815775,1726815785,1],["0600CO259",1726815813,1726815868,0],["0600CO19022",1726815853,1726815923,1],["0600CO19023",1726815882,1726815963,0],["0600CO000086",1726815901,1726815995,1],["0600CO235",1726815924,1726816035,1],["0600CO232",1726815955,1726816089,0],["0600CO229",1726816075,1726816158,0],["0600CO228",1726816134,1726816239,0],["0600CO18959",1726816201,1726816320,0]],[["0600CO216",1726849524,1726849516,0],["0600CO217",1726849575,1726849544,0],["0600CO227",1726849592,1726849560,1],["0600CO230",1726849654,1726849620,0],["0600CO231",1726849709,1726849654,0],["0600CO233",1726849729,1726849688,1],["0600CO234",1726849752,1726849726,1],["0600CO253",1726849781,1726849775,0],["0600CO261",1726849792,1726849813,0],["0600CO260",1726849812,1726849844,1],["0600CO19015",1726849849,1726849900,0],["3800C820002",1726849928,1726849949,0],["3800C863202",1726849998,1726850085,0],["3800C820102",1726850009,1726850123,1],["3800C819301",1726850036,1726850212,0],["3800C814902",1726850102,1726850256,0],["3800C864192",1726850177,1726850331,0],["3800C815900",1726850209,1726850400,0],["3800C851302",1726850453,1726850486,0],["3800C851501",1726850540,1726850560,0],["3800C852601",1726850600,1726850659,0],["3800C817100",1726850655,1726850712,0],["3800C852802",1726850673,1726850738,1],["3800C801500",1726850699,1726850776,0],["3800C892101",1726850736,1726850847,1],["3800C852402",1726850785,1726850940,0],["3800C801401",1726850877,1726850955,0],["3800C853302",1726850965,1726850989,0],["3800C817402",1726851012,1726851033,0],["3800C850901",1726851051,1726851086,0],["3800C850002",1726851091,1726851116,1],["3800C863102",1726851145,1726851156,0],["3800C825801",1726851167,1726851177,1],["3890D062702",1726851206,1726851215,0],["3890D062602",1726851230,1726851243,1],["3890D062502",1726851250,1726851266,1],["3890D062302",1726851331,1726851359,0],["3890D062202",1726851443,1726851389,0],["3890D062102",1726851463,1726851407,1],["3890D062002",1726851486,1726851428,1],["3890D061902",1726851515,1726851455,0],["3890D062901",1726851569,1726851480,0],["3890D056601",1726851595,1726851530,1],["3890D056701",1726851623,1726851582,0],["3890D027301",1726851690,1726851656,0],["3890D056901",1726851711,1726851703,1],["3890D057001",1726851739,1726851766,0],["3890D057101",1726851772,1726851801,1],["3890D050002",1726851810,1726851840,1],["3890D002602",1726851867,1726851900,0],["3890D002701",1726851916,1726851947,0],["3890D051802",1726852001,1726851998,0],["3890D051702",1726852024,1726852035,1],["3890D051602",1726852050,1726852077,0],["3890D051502",1726852074,1726852124,1],["3890D051402",1726852106,1726852187,1],["3890D051302",1726852118,1726852210,0],["3890D051202",1726852137,1726852274,1],["3800C597602",1726852158,1726852342,0],["3800C591802",1726852228,1726852419,0],["3800C506501",1726852260,1726852453,1],["3800C503101",1726852299,1726852494,0],["3800C509801",1726852355,1726852560,0],["3800C509600",1726852380,1726852589,1],["3800C518802",1726852409,1726852622,0],["3800C500901",1726852453,1726852675,1],["3800C592201",1726852486,1726852714,1],["3800C503601",1726852515,1726852749,1],["3800C592302",1726852572,1726852818,0],["3800C592402",1726852610,1726852848,1],["3800C592502",1726852636,1726852869,0],["3800C510100",1726852687,1726852920,0]]]}