{"meta":{"id":"825-york-road-sutton-on-the-forest-market-place-richmond","name":"825 - York Road Sutton on the Forest - Market Place Richmond","agency_name":"Reliance Motor Services","agency_noc":"RELD"},"line":"na","stops":{"3200YNA97133":{"name":"Hackfall Car Park","lon":-1.648481,"lat":54.193058,"bearing":315},"3200YNA97136":{"name":"Queens Head","lon":-1.641152,"lat":54.165043,"bearing":180},"3200YNA97137":{"name":"Swale View Caravan Park","lon":-1.797777,"lat":54.405731,"bearing":90},"3200YNA97138":{"name":"Swale View Caravan Park","lon":-1.797377,"lat":54.405651,"bearing":270},"3200YNA01390":{"name":"Station Road","lon":-1.281717,"lat":53.99934,"bearing":270},"3200YNA01391":{"name":"Station Road","lon":-1.281684,"lat":53.999466,"bearing":90},"3200YNA01392":{"name":"Nun Monkton Lane End","lon":-1.272345,"lat":53.998737,"bearing":90},"3200YNA01393":{"name":"Nun Monkten Lane End","lon":-1.273476,"lat":53.998653,"bearing":270},"3200YNA01394":{"name":"Moor Monkton Crossroads","lon":-1.220533,"lat":53.986855,"bearing":315},"3200YNA01395":{"name":"Moor Monkton Crossroads","lon":-1.219725,"lat":53.986794,"bearing":135},"3200YNA01667":{"name":"Market Place","lon":-1.829816,"lat":54.309753,"bearing":90},"3200YNA01668":{"name":"St Matthews Terr","lon":-1.824412,"lat":54.308201,"bearing":135},"3200YNA01669":{"name":"Middleham Road","lon":-1.824397,"lat":54.308029,"bearing":315},"3200YNA04998":{"name":"Studley Royal","lon":-1.575333,"lat":54.128242,"bearing":225},"3200YNA05101":{"name":"Grantley Lane End","lon":-1.629324,"lat":54.113968,"bearing":90},"3200YNA05103":{"name":"Grantley Lane End","lon":-1.629248,"lat":54.113922,"bearing":270},"3200YNA90285":{"name":"Cravengate","lon":-1.743465,"lat":54.404507,"bearing":270},"3200YNA90286":{"name":"The Old Convent","lon":-1.750564,"lat":54.404987,"bearing":90},"3200YNA90289":{"name":"Whitcliffe Place","lon":-1.7538,"lat":54.404808,"bearing":270},"3200YNA90870":{"name":"Visitor Centre","lon":-1.584292,"lat":54.113678,"bearing":90},"3200YNA90884":{"name":"Galphay Village Centre","lon":-1.613869,"lat":54.149158,"bearing":90},"3200YNA90885":{"name":"Galphay Village Centre","lon":-1.61387,"lat":54.149052,"bearing":270},"3200YNA90886":{"name":"St James Church","lon":-1.649217,"lat":54.182178,"bearing":135},"3200YNA90887":{"name":"St James Church","lon":-1.649355,"lat":54.182152,"bearing":315},"3200YNA90904":{"name":"Market Place","lon":-1.655888,"lat":54.222031,"bearing":90},"3200YNA90905":{"name":"School","lon":-1.779297,"lat":54.269375,"bearing":270},"3200YNA90907":{"name":"Wenslydale School","lon":-1.827068,"lat":54.312492,"bearing":225},"3200YNA90909":{"name":"Mount Drive","lon":-1.823642,"lat":54.315685,"bearing":0},"3200YNA90911":{"name":"Cross Keys Inn","lon":-1.824898,"lat":54.331306,"bearing":270},"3200YND10680":{"name":"The Odeon","lon":-1.534464,"lat":53.992443,"bearing":45},"3200YND10690":{"name":"North Park Rd","lon":-1.53056,"lat":53.992443,"bearing":90},"3200YND10700":{"name":"Christ Church","lon":-1.523802,"lat":53.993874,"bearing":45},"3200YND10720":{"name":"Leyland Rd","lon":-1.514641,"lat":53.995949,"bearing":90},"3200YND10730":{"name":"Rydal Road","lon":-1.509385,"lat":53.996681,"bearing":90},"3200YND10750":{"name":"Stonefall Ave","lon":-1.50364,"lat":53.997478,"bearing":45},"3200YND10770":{"name":"The Avenue","lon":-1.497179,"lat":54.00074,"bearing":45},"3200YND10790":{"name":"Golf Club","lon":-1.49031,"lat":54.004784,"bearing":45},"3200YND10810":{"name":"High Bridge","lon":-1.475433,"lat":54.008556,"bearing":225},"3200YND10820":{"name":"Council Offices","lon":-1.469836,"lat":54.01067,"bearing":180},"3200YND10825":{"name":"Bus Stn Stand C","lon":-1.46542,"lat":54.007622,"bearing":315},"3200YND10840":{"name":"High Bridge","lon":-1.475953,"lat":54.008461,"bearing":45},"3200YND10860":{"name":"Golf Club","lon":-1.491336,"lat":54.00449,"bearing":225},"3200YND10880":{"name":"The Avenue","lon":-1.497752,"lat":54.000023,"bearing":225},"3200YND10900":{"name":"Stonefall Ave","lon":-1.504253,"lat":53.997246,"bearing":225},"3200YND10930":{"name":"Leyland Rd","lon":-1.514139,"lat":53.995865,"bearing":270},"3200YND10940":{"name":"Granby Corner","lon":-1.518983,"lat":53.995121,"bearing":270},"3200YND10950":{"name":"Christ Church","lon":-1.52342,"lat":53.9939,"bearing":225},"3200YND10960":{"name":"North Park Rd","lon":-1.530835,"lat":53.992374,"bearing":270},"3200YND10970":{"name":"The Odeon","lon":-1.534939,"lat":53.992283,"bearing":270},"3200YND12580":{"name":"Redfearn's Garage","lon":-1.553512,"lat":54.009876,"bearing":315},"3200YND12590":{"name":"Knox Mill Lane","lon":-1.557454,"lat":54.01363,"bearing":315},"3200YND12600":{"name":"Warren Lodge","lon":-1.560473,"lat":54.016842,"bearing":315},"3200YND12610":{"name":"Otley Road","lon":-1.564808,"lat":54.022537,"bearing":0},"3200YND12611":{"name":"Addison Villas","lon":-1.563419,"lat":54.019665,"bearing":315},"3200YND12640":{"name":"Ripley Roundabout","lon":-1.565342,"lat":54.037315,"bearing":315},"3200YND12650":{"name":"Cross","lon":-1.567433,"lat":54.040318,"bearing":45},"3200YND12970":{"name":"Ripley Roundabout","lon":-1.564992,"lat":54.03717,"bearing":135},"3200YND12980":{"name":"Nidd Bridge","lon":-1.563614,"lat":54.034595,"bearing":180},"3200YND12990":{"name":"Daleside Nursery","lon":-1.564493,"lat":54.026447,"bearing":180},"3200YND13000":{"name":"Otley Road","lon":-1.564589,"lat":54.023075,"bearing":180},"3200YND13010":{"name":"Addison Villas","lon":-1.562964,"lat":54.019394,"bearing":135},"3200YND13030":{"name":"Knox Mill Lane","lon":-1.557347,"lat":54.013657,"bearing":135},"3200YND13040":{"name":"Redfearn's Garage","lon":-1.552017,"lat":54.008369,"bearing":135},"3200YND13050":{"name":"West Street","lon":-1.550117,"lat":54.006233,"bearing":135},"3200YND13060":{"name":"Hydro","lon":-1.548875,"lat":54.004002,"bearing":180},"3200YND13070":{"name":"Oakdale Avenue","lon":-1.547386,"lat":54.000641,"bearing":180},"3200YND13100":{"name":"Cheltenham Crescent","lon":-1.542547,"lat":53.995285,"bearing":90},"3200YND23120":{"name":"Valley View","lon":-1.618687,"lat":54.046116,"bearing":270},"3200YND56740":{"name":"Nidderdale Lodge","lon":-1.441644,"lat":54.006779,"bearing":90},"3200YND56750":{"name":"Caravan Park","lon":-1.434163,"lat":54.007118,"bearing":90},"3200YND56930":{"name":"Nidderdale Lodge Park","lon":-1.442427,"lat":54.006367,"bearing":270},"3200YND56940":{"name":"Princess Drive","lon":-1.455896,"lat":54.005466,"bearing":270},"3200YND57820":{"name":"Asda","lon":-1.53681,"lat":53.995506,"bearing":270},"3200YND81000":{"name":"Victoria Avenue","lon":-1.538053,"lat":53.990639,"bearing":270},"3200YNE04351":{"name":"Starbeck Crossing","lon":-1.499444,"lat":53.998825,"bearing":45},"3200YNE04463":{"name":"Victoria Road","lon":-1.740877,"lat":54.404537,"bearing":90},"3200YNE04464":{"name":"Victoria Road","lon":-1.740893,"lat":54.404465,"bearing":270},"3200YNE04707":{"name":"Hall","lon":-1.741633,"lat":54.266899,"bearing":180},"3200YNA96393":{"name":"Royal Hall","lon":-1.544741,"lat":53.995564,"bearing":135},"3200YNA96422":{"name":"Princess Drive","lon":-1.455849,"lat":54.005604,"bearing":90},"3200YNA96471":{"name":"Market Cross","lon":-1.805739,"lat":54.285343,"bearing":225},"3200YNA96491":{"name":"Bus Stn Stand B","lon":-1.465175,"lat":54.007648,"bearing":135},"3200YNA96802":{"name":"Friary Gardens","lon":-1.737009,"lat":54.404781,"bearing":0},"3200YNA96600":{"name":"Lane End","lon":-1.359124,"lat":54.009098,"bearing":270},"3290YYA00003":{"name":"Langley Gate","lon":-1.141867,"lat":53.972153,"bearing":315},"3290YYA00004":{"name":"Langley Gate","lon":-1.139796,"lat":53.972042,"bearing":90},"3290YYA00005":{"name":"Low Poppleton Lane","lon":-1.132032,"lat":53.969322,"bearing":135},"3290YYA00008":{"name":"Plantation Drive","lon":-1.126664,"lat":53.966461,"bearing":315},"3290YYA00010":{"name":"Cranbrook Avenue","lon":-1.12373,"lat":53.965389,"bearing":135},"3290YYA00011":{"name":"Ouse Acres","lon":-1.122191,"lat":53.964634,"bearing":315},"3290YYA00013":{"name":"Malvern Avenue","lon":-1.118128,"lat":53.963596,"bearing":315},"3290YYA00014":{"name":"Seldon Road","lon":-1.11516,"lat":53.961967,"bearing":135},"3290YYA00016":{"name":"Grantham Drive","lon":-1.11169,"lat":53.959557,"bearing":135},"3290YYA00017":{"name":"Grantham Drive","lon":-1.111499,"lat":53.959187,"bearing":315},"3290YYA00020":{"name":"Fox Inn","lon":-1.105754,"lat":53.954868,"bearing":315},"3290YYA00021":{"name":"Fox Inn","lon":-1.105963,"lat":53.955074,"bearing":135},"3290YYA00080":{"name":"York St John University","lon":-1.082244,"lat":53.96722,"bearing":45},"3290YYA00081":{"name":"York St John University","lon":-1.082156,"lat":53.967041,"bearing":180},"3290YYA00082":{"name":"York Hospital","lon":-1.081516,"lat":53.96912,"bearing":180},"3290YYA00118":{"name":"Exhibition Square","lon":-1.085625,"lat":53.962456,"bearing":0},"3290YYA00122":{"name":"Theatre Royal","lon":-1.085346,"lat":53.961994,"bearing":180},"3290YYA00128":{"name":"Station Road","lon":-1.089332,"lat":53.958836,"bearing":225},"3290YYA00130":{"name":"Station Avenue (Stop RM)","lon":-1.089701,"lat":53.959366,"bearing":45},"3290YYA00137":{"name":"Rail Station (Stop RJ)","lon":-1.091914,"lat":53.957809,"bearing":180},"3290YYA00140":{"name":"Rail Station (Stop RA)","lon":-1.092218,"lat":53.957867,"bearing":0},"3290YYA00149":{"name":"Blossom Street","lon":-1.091698,"lat":53.95512,"bearing":225},"3290YYA00152":{"name":"Blossom Street","lon":-1.092958,"lat":53.954662,"bearing":45},"3290YYA00181":{"name":"Gillygate","lon":-1.083616,"lat":53.964397,"bearing":225},"3290YYA00182":{"name":"Gillygate","lon":-1.083471,"lat":53.964756,"bearing":45},"3290YYA00192":{"name":"Holgate Hill","lon":-1.100962,"lat":53.953781,"bearing":270},"3290YYA00193":{"name":"Cambridge Street","lon":-1.095352,"lat":53.953873,"bearing":225},"3290YYA00195":{"name":"Holgate Hill","lon":-1.101869,"lat":53.954121,"bearing":90},"3290YYA00311":{"name":"Feversham Crescent","lon":-1.081995,"lat":53.971596,"bearing":180},"3290YYA00670":{"name":"Hessay A59","lon":-1.19907,"lat":53.980774,"bearing":90},"3290YYA00877":{"name":"Low Poppleton Lane","lon":-1.132096,"lat":53.969173,"bearing":315},"3290YYA01090":{"name":"Hessay A59","lon":-1.199133,"lat":53.980629,"bearing":270},"3290YYA01094":{"name":"Reliance Garage","lon":-1.099398,"lat":54.039101,"bearing":180},"3290YYA01096":{"name":"Moor Farm","lon":-1.097988,"lat":54.021679,"bearing":0},"3290YYA01098":{"name":"Home Farm","lon":-1.098252,"lat":54.018642,"bearing":180},"3290YYA01099":{"name":"Wigginton Road Roundabout","lon":-1.090043,"lat":53.995483,"bearing":180},"3290YYA01103":{"name":"Kettlestring Grange","lon":-1.086479,"lat":53.989632,"bearing":180},"3290YYA01104":{"name":"Nestle Rowntree","lon":-1.082027,"lat":53.974319,"bearing":180},"3290YYA01648":{"name":"Willow House Caravan Park","lon":-1.092794,"lat":54.002937,"bearing":180},"3290YYA01662":{"name":"Garden Centre","lon":-1.145558,"lat":53.972836,"bearing":90},"3290YYA01663":{"name":"Red Lion A59","lon":-1.163335,"lat":53.975063,"bearing":270},"3200YND56920":{"name":"Caravan Park","lon":-1.434697,"lat":54.007095,"bearing":270},"3200YNA96543":{"name":"The Paddock","lon":-1.450005,"lat":54.005611,"bearing":270},"3290YYA01661":{"name":"Garden Centre","lon":-1.14588,"lat":53.972733,"bearing":270},"3290YYA01095":{"name":"Moor Farm","lon":-1.097331,"lat":54.022411,"bearing":225},"3200YNA97134":{"name":"Hackfall Car Park","lon":-1.64822,"lat":54.19305,"bearing":135},"3200YNA90883":{"name":"The Galphay Arms","lon":-1.614858,"lat":54.14978,"bearing":135},"3200YNA90910":{"name":"Dale Grove","lon":-1.823504,"lat":54.315678,"bearing":180},"3200YND23200":{"name":"Whipley Bank Farm","lon":-1.591745,"lat":54.049477,"bearing":90},"3200YNE04326":{"name":"The Vicarage","lon":-1.829633,"lat":54.376385,"bearing":135},"3200YNA96470":{"name":"Market Place","lon":-1.805648,"lat":54.28513,"bearing":225},"3200YNA96602":{"name":"Brimham Rocks","lon":-1.681734,"lat":54.075615,"bearing":0}},"trips":[[["3200YNE04464",1727100967,1727100933],["3200YNA90285",1727101009,1727100954],["3200YNA90289",1727101079,1727101036],["3200YNA97138",1727101343,1727101380],["3200YNE04326",1727101622,1727101693],["3200YNA90911",1727102173,1727102100],["3200YNA90910",1727102285,1727102280],["3200YNA90907",1727102369,1727102340],["3200YNA01667",1727102425,1727102400],["3200YNA01668",1727102498,1727102437],["3200YNA96471",1727102732,1727102700],["3200YNE04707",1727103173,1727103180],["3200YNA90904",1727103782,1727103780],["3200YNA97134",1727104502,1727104500],["3200YNA90886",1727104596,1727104620],["3200YNA97136",1727104889,1727104980],["3200YNA90884",1727105253,1727105296],["3200YNA90883",1727105264,1727105280],["3200YNA04998",1727106048,1727105884],["3200YNA90870",1727106134,1727106180],["3200YNA05103",1727106723,1727106420],["3200YND12970",1727108157,1727107856],["3200YND12980",1727108217,1727107903],["3200YND12990",1727108276,1727108045],["3200YND23200",1727108306,1727107560],["3200YND13010",1727108346,1727108170],["3200YND13040",1727108421,1727108392],["3200YND13050",1727108472,1727108434],["3200YND13070",1727108529,1727108536],["3200YNA96393",1727108585,1727108629],["3200YND13000",1727108697,1727108104],["3200YND13030",1727108765,1727108285],["3200YND10680",1727108884,1727108740],["3200YND13060",1727108937,1727108475],["3200YND10690",1727108955,1727108772],["3200YND10700",1727108999,1727108832],["3200YND10730",1727109079,1727108959],["3200YND13100",1727109124,1727108652],["3200YNE04351",1727109145,1727109048],["3200YND10790",1727109205,1727109164],["3200YND10840",1727109267,1727109294],["3200YND10820",1727109328,1727109362],["3200YNA96491",1727109382,1727109420],["3200YNA96422",1727109436,1727109452],["3200YND10720",1727109448,1727108914],["3200YND56740",1727109493,1727109499],["3200YND10750",1727109505,1727109008],["3200YND56750",1727109542,1727109523],["3200YND10770",1727109559,1727109081],["3200YNA01391",1727110058,1727110020],["3200YNA01392",1727110100,1727110080],["3290YYA00670",1727110341,1727110320],["3200YNA01395",1727110950,1727110200],["3290YYA01662",1727111244,1727110620],["3290YYA00004",1727111290,1727110661],["3290YYA00005",1727111375,1727110723],["3290YYA00010",1727111424,1727110796],["3290YYA00014",1727111494,1727110867],["3290YYA00016",1727111555,1727110904],["3290YYA00021",1727111614,1727110969],["3290YYA00195",1727111641,1727111000],["3290YYA00152",1727111776,1727111062],["3290YYA00140",1727111833,1727111100],["3290YYA00130",1727111891,1727111163],["3290YYA00118",1727112099,1727111280],["3290YYA00182",1727112149,1727111340],["3290YYA00080",1727112199,1727111400],["3290YYA01096",1727112732,1727111868]],[["3290YYA01094",1727078469,1727078520],["3290YYA01095",1727078568,1727078633],["3290YYA01098",1727078584,1727078659],["3290YYA01648",1727078733,1727078767],["3290YYA01099",1727078788,1727078818],["3290YYA01103",1727078829,1727078860],["3290YYA01104",1727078941,1727078965],["3290YYA00082",1727079002,1727079000],["3290YYA00311",1727079024,1727078983],["3290YYA00081",1727079080,1727079060],["3290YYA00181",1727079198,1727079120],["3290YYA00122",1727079241,1727079180],["3290YYA00128",1727079278,1727079240],["3290YYA00137",1727079571,1727079600],["3290YYA00149",1727079698,1727079631],["3290YYA00192",1727079766,1727079697],["3290YYA00193",1727079777,1727079659],["3290YYA00020",1727079840,1727079732],["3290YYA00017",1727079891,1727079795],["3290YYA00013",1727079964,1727079863],["3290YYA00011",1727079989,1727079893],["3290YYA00008",1727080027,1727079930],["3290YYA00877",1727080062,1727079978],["3290YYA00003",1727080152,1727080052],["3290YYA01661",1727080240,1727080080],["3290YYA01663",1727080266,1727080155],["3290YYA01090",1727080377,1727080309],["3200YNA01394",1727080450,1727080409],["3200YNA01393",1727080627,1727080645],["3200YNA01390",1727080736,1727080680],["3200YNA96600",1727080905,1727080986],["3200YND56930",1727081253,1727081308],["3200YND56940",1727081309,1727081361],["3200YND56920",1727081322,1727081278],["3200YNA96543",1727081394,1727081338],["3200YND10825",1727081411,1727081400],["3200YND10810",1727081537,1727081499],["3200YND10860",1727081605,1727081626],["3200YND10880",1727081674,1727081700],["3200YND10900",1727081725,1727081853],["3200YND10930",1727081796,1727082039],["3200YND10940",1727081844,1727082131],["3200YND10950",1727081890,1727082221],["3200YND10970",1727081972,1727082441],["3200YND57820",1727082139,1727082547],["3200YND10960",1727082171,1727082365],["3200YND81000",1727082959,1727082946],["3200YND12580",1727083287,1727083241],["3200YND12600",1727083345,1727083350],["3200YND12610",1727083396,1727083435],["3200YND12590",1727083400,1727083300],["3200YND12611",1727083474,1727083395],["3200YND12640",1727083524,1727083636],["3200YND12650",1727083633,1727083680],["3200YND23120",1727083948,1727084026],["3200YNA96602",1727084779,1727084400],["3200YNA05101",1727085175,1727084820],["3200YNA90870",1727086026,1727085300],["3200YNA90885",1727086704,1727086440],["3200YNA90887",1727087423,1727087160],["3200YNA97133",1727087576,1727087280],["3200YNA90904",1727087938,1727087700],["3200YNA90905",1727088935,1727088420],["3200YNA96470",1727089423,1727088780],["3200YNA01669",1727089445,1727089020],["3200YNA01667",1727089695,1727089200],["3200YNA90909",1727089755,1727089292],["3200YNA97137",1727090761,1727090100],["3200YNA90286",1727091035,1727090700],["3200YNE04463",1727091139,1727090760],["3200YNA96802",1727091265,1727090820]]]}